Workbook

Sheet Rankings
A1: Rank | B1: Company | C1: Category | D1: City | E1: LT entity and company code | F1: Lithuanian team size | G1: Typical entry roles | H1: Advertised entry/junior pay (EUR gross/month, text range) | I1: Entity average pay (EUR gross/month) | J1: Entity average pay date and basis | K1: Pay score (1 to 10) | L1: Prestige score (1 to 10) | M1: Fit for HEC MIF profile (1 to 10) | N1: Accessibility / hiring likelihood (1 to 10) | O1: Learning and exit opportunities (1 to 10) | P1: Weighted total | Q1: Tier | R1: Hiring channel / how to get in | S1: Key notes and red flags | T1: Data confidence | U1: Main source URL
A2: =RANK(P2,$P$2:$P$85,0) -> 1 | B2: Covalis Capital (Vilnius equity research team) | C2: Hedge fund (equity long/short) | D2: Vilnius (HQ London) | E2: No Lithuanian UAB found; Covalis Capital LLP (UK, OC375146); Cayman funds | F2: At least 2 equity analysts in Vilnius; about 31 staff globally on LinkedIn | G2: Equity Research Analyst, Equity Analyst (infrastructure, utilities, renewables, industrials, materials) | H2: Not advertised (no public job ads found) | J2: n/a (no Lithuanian entity, so no Sodra data) | K2: 8 | L2: 9 | M2: 10 | N2: 2 | O2: 9 | P2: =IF(Weights!$B$7=0,0,ROUND((K2*Weights!$B$2+L2*Weights!$B$3+M2*Weights!$B$4+N2*Weights!$B$5+O2*Weights!$B$6)/Weights!$B$7,2)) -> 7.9 | Q2: =IF(P2>=Weights!$B$11,"A",IF(P2>=Weights!$B$12,"B","C")) -> A | R2: Networking and direct approach: Vilnius analysts on LinkedIn (Rokas Jusys, Vaidas Ališauskas), referral, approach via London HQ; Lithuanian-born founder/CIO Zach Mecelis | S2: Only foreign hedge fund confirmed with investment staff in Vilnius; covers about 300 companies in 30 countries. Pay score is inferred (no data). No evidence of fresh-grad hiring or internships. Activist profile (failed Enel slate, 2023). | T2: Medium | U2: https://www.linkedin.com/company/covalis-capital-llp
A3: =RANK(P3,$P$2:$P$85,0) -> 2 | B3: INVL Asset Management: Private Equity (INVL PE Fund II, European Banking Opportunities Fund) | C3: Private equity | D3: Vilnius | E3: INVL Asset Management, UAB, 126263073 | F3: 85 to 95 at entity (about 150 group); PE team has investment managers, an associate and junior analysts | G3: Junior Analyst (PE), Investment Valuation Analyst, Fund Finance Analyst | H3: Investment Valuation Analyst 2,900 to 3,500 plus bonus (2+ years); Fund Finance Manager Assistant/Analyst 1,300 to 1,700 base; junior investment accounting 1,500 to 2,000 plus bonus | I3: 5120 | J3: 2025 (tax.lt); 5,143 to 5,636 on other aggregators; entity-wide incl. back office | K3: 7 | L3: 8 | M3: 9 | N3: 6 | O3: 8 | P3: =IF(Weights!$B$7=0,0,ROUND((K3*Weights!$B$2+L3*Weights!$B$3+M3*Weights!$B$4+N3*Weights!$B$5+O3*Weights!$B$6)/Weights!$B$7,2)) -> 7.65 | Q3: =IF(P3>=Weights!$B$11,"A",IF(P3>=Weights!$B$12,"B","C")) -> A | R3: INVL careers page, cvbankas, LinkedIn; valuation and fund finance roles are side doors into the deal team | S3: Largest Vilnius PE employer: Fund II closed at a record EUR 410m; new EUR 200m CEE bank fund approved 8 Oct 2026 (first close targeted end-2026), likely adding junior seats. Junior pay about 2,000 to 3,500, well below the entity average. | T3: High | U3: https://invl.com/en/investments/invl-private-equity-fund-ii/
A4: =RANK(P4,$P$2:$P$85,0) -> 3 | B4: BaltCap (Vilnius office) | C4: Private equity and infrastructure | D4: Vilnius (HQ Tallinn) | E4: BaltCap UAB, 111764858 (GP vehicles e.g. BaltCap Investments GP2 UAB, 302496797) | F4: 8 insured at UAB; 35+ investment professionals pan-Baltic | G4: Investment Associate, Analyst (buyout, growth, infrastructure) | H4: Not advertised | I4: 5646 | J4: 2026 YTD (Scoris); 5,001 (okredo); 8 staff incl. partners | K4: 6 | L4: 8 | M4: 9 | N4: 3 | O4: 8 | P4: =IF(Weights!$B$7=0,0,ROUND((K4*Weights!$B$2+L4*Weights!$B$3+M4*Weights!$B$4+N4*Weights!$B$5+O4*Weights!$B$6)/Weights!$B$7,2)) -> 6.95 | Q4: =IF(P4>=Weights!$B$11,"A",IF(P4>=Weights!$B$12,"B","C")) -> A | R4: Direct approach to Vilnius directors (Marius Miškinis, Robertas Petrauskas); LT VCA events; associates usually hired after 1 to 2 years in Big 4 TS or IB | S4: Pan-Baltic buyout leader (Fund III EUR 177m; Infrastructure Fund II EUR 200m; Growth Fund). Red flag: EPPO investigation of a former Lithuanian infrastructure partner (alleged misappropriation over EUR 42m); check the case status before applying. | T4: High | U4: https://www.baltcap.com/team/
A5: =RANK(P5,$P$2:$P$85,0) -> 4 | B5: Livonia Partners (Vilnius office) | C5: Private equity (buyout) | D5: Vilnius (HQ Riga or Tallinn; sources conflict) | E5: No Lithuanian UAB code found | F5: Small Vilnius team around partner Mindaugas Utkevičius (headcount unknown) | G5: Investment Analyst, Associate | H5: Not advertised | J5: n/a | K5: 6 | L5: 8 | M5: 9 | N5: 2 | O5: 8 | P5: =IF(Weights!$B$7=0,0,ROUND((K5*Weights!$B$2+L5*Weights!$B$3+M5*Weights!$B$4+N5*Weights!$B$5+O5*Weights!$B$6)/Weights!$B$7,2)) -> 6.8 | Q5: =IF(P5>=Weights!$B$11,"A",IF(P5>=Weights!$B$12,"B","C")) -> A | R5: Direct approach to the Vilnius partner; LT VCA; timing around the Fund III first close | S5: Fund II EUR 157m; Fund III being raised (EBRD up to EUR 30m approved May 2026; total project cost EUR 225m), its largest yet. Pay score inferred from BaltCap. | T5: Medium | U5: https://www.ebrd.com/home/work-with-us/projects/psd/56209.html
A6: =RANK(P6,$P$2:$P$85,0) -> 5 | B6: Ignitis Group (Energy Trading: power, gas and LNG) | C6: Energy trading | D6: Vilnius | E6: AB Ignitis grupė and subsidiaries (codes unverified; notes cite 301844044 and 303383884 from memory) | F6: Trading headcount unknown (group about 4,851) | G6: Quantitative Trading Analyst, Market Analyst (Power Trading), Hedge Power Analyst, Power Trader-Analyst (evening shift), Senior Quantitative Researcher | H6: Quant Trading Analyst 3,267 to 4,900; Senior Power Trading Analyst 3,156 to 4,735; Power Trader-Analyst 3,124 to 4,686; Market Analyst 3,430 to 5,150; Senior Quant Researcher 3,430 to 5,150 plus variable | I6: 5802 | J6: Jul 2026 group median (press), not trading specific | K6: 7 | L6: 7 | M6: 7 | N6: 5 | O6: 7 | P6: =IF(Weights!$B$7=0,0,ROUND((K6*Weights!$B$2+L6*Weights!$B$3+M6*Weights!$B$4+N6*Weights!$B$5+O6*Weights!$B$6)/Weights!$B$7,2)) -> 6.7 | Q6: =IF(P6>=Weights!$B$11,"A",IF(P6>=Weights!$B$12,"B","C")) -> A | R6: Ignitis careers site, cvbankas, cvonline, MeetFrank, Built In; Young Talents internships (not trading specific) | S6: Only utility with an evidenced, actively hiring trading desk in Lithuania. Long-term LNG contract (Sep 2026) and Chief Trading Officer posting suggest growth. Some roles are shift-based; fresh-grad eligibility per role not confirmed. Regionally capped versus Nordic desks. | T6: High | U6: https://www.cvbankas.lt/market-analyst-power-trading-vilniuje/1-14112520
A7: =RANK(P7,$P$2:$P$85,0) -> 6 | B7: KPMG Baltics (Deal Advisory) | C7: Big 4 transaction services / M&A | D7: Vilnius | E7: KPMG Baltics, UAB, 111494971 | F7: 170 to 286 insured (company-wide) | G7: Intern, Senior Analyst in Deal Advisory | H7: Interns 1,153 to 1,245; Senior Analyst Deal Advisory 1,900 to 2,500; Senior 2,500 to 3,500 | I7: 3864 | J7: Apr 2026 (info.lt); 3,711 for 2026 (pinokis); company-wide | K7: 4 | L7: 6 | M7: 8 | N7: 8 | O7: 8 | P7: =IF(Weights!$B$7=0,0,ROUND((K7*Weights!$B$2+L7*Weights!$B$3+M7*Weights!$B$4+N7*Weights!$B$5+O7*Weights!$B$6)/Weights!$B$7,2)) -> 6.5 | Q7: =IF(P7>=Weights!$B$11,"A",IF(P7>=Weights!$B$12,"B","C")) -> A | R7: KPMG internships, cvbankas | S7: Mergermarket Baltics Financial Adviser of the Year 2023; publishes the quarterly Baltic M&A/PE/VC overview. | T7: High | U7: https://www.cvbankas.lt/senior-in-deal-advisory-team-vilniuje/1-11236906
A8: =RANK(P8,$P$2:$P$85,0) -> 6 | B8: PwC Lithuania (Deals) | C8: Big 4 transaction services / M&A | D8: Vilnius | E8: PricewaterhouseCoopers UAB (code not confirmed) | F8: Not found | G8: Deals Consultant, Senior Consultant in Deals | H8: Senior Consultant in Deals 2,500 to 4,000 (entry likely lower) | J8: n/a | K8: 4 | L8: 6 | M8: 8 | N8: 8 | O8: 8 | P8: =IF(Weights!$B$7=0,0,ROUND((K8*Weights!$B$2+L8*Weights!$B$3+M8*Weights!$B$4+N8*Weights!$B$5+O8*Weights!$B$6)/Weights!$B$7,2)) -> 6.5 | Q8: =IF(P8>=Weights!$B$11,"A",IF(P8>=Weights!$B$12,"B","C")) -> A | R8: Big 4 internships and trainee intakes, cvbankas, LinkedIn | S8: #1 Baltic M&A adviser by volume in 2024 (8 deals). Structured training; classic exit to PE and corporate development. | T8: High | U8: https://www.cvbankas.lt/senior-consultant-in-deals-vilniuje/1-11489670
A9: =RANK(P9,$P$2:$P$85,0) -> 8 | B9: VNT Technologies (VNTrading) | C9: Quant research / algorithmic trading | D9: Vilnius | E9: VNT Technologies, UAB (also VNTrading, UAB), 306700560 | F9: 6 to 13 | G9: Signal Processing Researcher (quant researcher), Python Developer | H9: Researcher base 5,000 to 10,000 plus year-end bonus | I9: 4578 | J9: May 2026 (info.lt); 5,573 as 2025 average (Scoris); 4,017 for 2026 YTD | K9: 10 | L9: 7 | M9: 4 | N9: 2 | O9: 7 | P9: =IF(Weights!$B$7=0,0,ROUND((K9*Weights!$B$2+L9*Weights!$B$3+M9*Weights!$B$4+N9*Weights!$B$5+O9*Weights!$B$6)/Weights!$B$7,2)) -> 6.4 | Q9: =IF(P9>=Weights!$B$11,"A",IF(P9>=Weights!$B$12,"B","C")) -> B | R9: Own careers site; no finance experience required; hires Oxbridge, olympiad medallists and PhDs | S9: Highest posted quant salary range in Lithuania. Very small and young (registered Mar 2024) but profitable (2025 profit about EUR 1.6m). Fit is low for a finance-only profile: maths and signal processing first. | T9: High | U9: https://vnttechnologies.com/quantitative-researcher
A10: =RANK(P10,$P$2:$P$85,0) -> 8 | B10: Ignitis Group (Group Treasury, IR, Investments and M&A) | C10: Corporate finance | D10: Vilnius | E10: AB Ignitis grupė; Ignitis Renewables (codes not verified) | F10: Not found | G10: FP&A trainee, Senior Financial Analyst, Group Treasury and IR analyst; Investment Project Manager needs 5+ years | H10: FP&A trainee 1,240 to 1,860; Senior Financial Analyst (Ignitis Renewables) 2,770 to 4,150; Chief Financial Controller 3,430 to 5,150 | I10: 5802 | J10: Jul 2026 group median (press) | K10: 6 | L10: 6 | M10: 8 | N10: 6 | O10: 6 | P10: =IF(Weights!$B$7=0,0,ROUND((K10*Weights!$B$2+L10*Weights!$B$3+M10*Weights!$B$4+N10*Weights!$B$5+O10*Weights!$B$6)/Weights!$B$7,2)) -> 6.4 | Q10: =IF(P10>=Weights!$B$11,"A",IF(P10>=Weights!$B$12,"B","C")) -> B | R10: Ignitis Young Talents programme and internships; careers site | S10: Highest Sodra median among state-owned firms; listed on Nasdaq Vilnius and LSE; dedicated Investments and M&A function (senior hiring). | T10: High | U10: https://ignitisgrupe.lt/en/career/young-talents
A11: =RANK(P11,$P$2:$P$85,0) -> 10 | B11: INVL Asset Management: Renewable Energy Fund I | C11: Infrastructure / energy transition | D11: Vilnius | E11: INVL Asset Management, UAB, 126263073 | F11: Small fund team (managing partner, partner, analyst) | G11: Analyst | H11: Not advertised; comparable recruiter ad (renewables Investment Analyst) 3,000 to 4,000 with 2+ years | I11: 5120 | J11: 2025 entity-wide (tax.lt) | K11: 6 | L11: 7 | M11: 8 | N11: 3 | O11: 7 | P11: =IF(Weights!$B$7=0,0,ROUND((K11*Weights!$B$2+L11*Weights!$B$3+M11*Weights!$B$4+N11*Weights!$B$5+O11*Weights!$B$6)/Weights!$B$7,2)) -> 6.35 | Q11: =IF(P11>=Weights!$B$11,"A",IF(P11>=Weights!$B$12,"B","C")) -> B | R11: INVL careers, LinkedIn; network with fund partners | S11: Solar portfolio in Romania and Poland with EBRD and Eiffel debt. Fund term to Aug 2028, so seats depend on successor vehicles. | T11: Medium | U11: https://invl.com/en/investments/invl-renewable-energy-fund-i/
A12: =RANK(P12,$P$2:$P$85,0) -> 11 | B12: Humbility | C12: Quant/prop trading (crypto HFT and arbitrage) | D12: Vilnius | E12: Humbility, UAB, 305825881 | F12: 46 to 51 (Apr 2026) | G12: Junior Software Engineer, trading/quant developer | H12: Not stated; annual profit sharing on top of base | I12: 6183 | J12: Jan 2026 (Scoris); 9,270 as 2025 average on one site; bonus-month spike about 40,318 (Apr 2026) | K12: 9 | L12: 7 | M12: 4 | N12: 3 | O12: 7 | P12: =IF(Weights!$B$7=0,0,ROUND((K12*Weights!$B$2+L12*Weights!$B$3+M12*Weights!$B$4+N12*Weights!$B$5+O12*Weights!$B$6)/Weights!$B$7,2)) -> 6.3 | Q12: =IF(P12>=Weights!$B$11,"A",IF(P12>=Weights!$B$12,"B","C")) -> B | R12: Own website, LinkedIn, MeetFrank, Tradermath; targets STEM, olympiad and Oxbridge/Imperial profiles | S12: First large-scale crypto trading firm in Lithuania. Tech-heavy: a finance MSc is competitive only with strong coding and statistics. Crypto market and regulatory risk. Registered as computer programming, so finance-code Sodra screens miss it. | T12: High | U12: https://scoris.lt/imone/305825881/darbuotojai_atlyginimai
A13: =RANK(P13,$P$2:$P$85,0) -> 11 | B13: INVL Asset Management: Bridge Finance (private debt) | C13: Private credit | D13: Vilnius | E13: INVL Asset Management, UAB, 126263073 (Mundus merged in) | F13: Small team (not found) | G13: Credit/investment analyst | H13: Not advertised | I13: 5120 | J13: 2025 entity-wide (tax.lt) | K13: 6 | L13: 6 | M13: 9 | N13: 3 | O13: 7 | P13: =IF(Weights!$B$7=0,0,ROUND((K13*Weights!$B$2+L13*Weights!$B$3+M13*Weights!$B$4+N13*Weights!$B$5+O13*Weights!$B$6)/Weights!$B$7,2)) -> 6.3 | Q13: =IF(P13>=Weights!$B$11,"A",IF(P13>=Weights!$B$12,"B","C")) -> B | R13: INVL careers, LinkedIn; Baltic Private Debt Forum | S13: INVL bought out Mundus (2023) and merged it in; NAV EUR 32.5m (Jun 2024); an executive cited a EUR 100m+ private debt fund to fill a bank-lending gap. | T13: Medium | U13: https://invaldainvl.com/en/group-company-press-releases/invl-group-completes-the-acquisition-of-the-mundus-private-debt-fund-management-company
A14: =RANK(P14,$P$2:$P$85,0) -> 11 | B14: Revolut Bank (Treasury, ALM, portfolio management) | C14: Fintech bank | D14: Vilnius | E14: Revolut Bank, UAB, 304580906 | F14: 108 to 128 | G14: Treasury/ALM analyst, Portfolio Manager (EU Bank), credit risk, finance | H14: ALM Treasury Manager 3,600 to 4,200; Portfolio Manager EU Bank 3,800 to 4,200 | I14: 5507 | J14: Apr 2026 (tax.lt); 5,812 Aug 2026 (1551.lt) | K14: 7 | L14: 6 | M14: 7 | N14: 4 | O14: 7 | P14: =IF(Weights!$B$7=0,0,ROUND((K14*Weights!$B$2+L14*Weights!$B$3+M14*Weights!$B$4+N14*Weights!$B$5+O14*Weights!$B$6)/Weights!$B$7,2)) -> 6.3 | Q14: =IF(P14>=Weights!$B$11,"A",IF(P14>=Weights!$B$12,"B","C")) -> B | R14: Revolut careers, LinkedIn; Lithuania Head of Treasury | S14: ECB-licensed bank HQ in Vilnius. Senior-heavy licensed entity; operations staff sit in other entities on far lower pay (FinCrime Analyst about 20,000 to 25,000 per year). | T14: High | U14: https://tax.lt/imones/101691-revolut-bank-uab
A15: =RANK(P15,$P$2:$P$85,0) -> 11 | B15: SEB (Corporate Banking and Project Finance) | C15: Bank CIB | D15: Vilnius | E15: SEB bankas AB (code not verified) | F15: Not found for CIB | G15: Client Analyst (corporate credit), Advisory Manager/Client Associate in Project Finance, Loan Officer (Structured Loans) | H15: Loan Officer Structured Loans 1,950 to 2,800; Liquidity Services specialist 1,950 to 2,800 | I15: 3830 | J15: 2026 bank-wide (pinokis) | K15: 5 | L15: 6 | M15: 8 | N15: 6 | O15: 7 | P15: =IF(Weights!$B$7=0,0,ROUND((K15*Weights!$B$2+L15*Weights!$B$3+M15*Weights!$B$4+N15*Weights!$B$5+O15*Weights!$B$6)/Weights!$B$7,2)) -> 6.3 | Q15: =IF(P15>=Weights!$B$11,"A",IF(P15>=Weights!$B$12,"B","C")) -> B | R15: SEB careers (Lever), cvbankas | S15: Most IB-like bank seats in Vilnius: leveraged finance, fund financing, PPP, infrastructure, renewables. ECM and M&A execution sits in Stockholm. | T15: High | U15: https://jobs.eu.lever.co/seb/e5529a61-aa06-466d-baaf-da9eced457b4
A16: =RANK(P16,$P$2:$P$85,0) -> 11 | B16: Vinted (Treasury, FP&A) | C16: Corporate finance (tech) | D16: Vilnius / Kaunas | E16: Vinted, UAB, 302767152 (also Vinted Pay, Vinted Go) | F16: 1,705 to 1,816 | G16: Senior Treasury Analyst, Financial Planning Analyst, Finance Control Analyst, Pricing | H16: Senior Treasury Analyst 3,233 to 4,383; Financial Planning Analyst 3,433 to 4,650 | I16: 4748 | J16: Aug 2026 (topimones); 5,075 Jul 2026 (info.lt) | K16: 7 | L16: 6 | M16: 7 | N16: 5 | O16: 6 | P16: =IF(Weights!$B$7=0,0,ROUND((K16*Weights!$B$2+L16*Weights!$B$3+M16*Weights!$B$4+N16*Weights!$B$5+O16*Weights!$B$6)/Weights!$B$7,2)) -> 6.3 | Q16: =IF(P16>=Weights!$B$11,"A",IF(P16>=Weights!$B$12,"B","C")) -> B | R16: careers.vinted.com | S16: Average includes many engineers. Treasury role covers capital and short-term liquidity management. | T16: High | U16: https://careers.vinted.com/jobs/j/4848497101
A17: =RANK(P17,$P$2:$P$85,0) -> 16 | B17: Bank of Lithuania (Lietuvos bankas) | C17: Central bank / regulator | D17: Vilnius | E17: Lietuvos bankas | F17: About 677 (end-2024) | G17: Intern, specialist (market operations, financial stability, supervision) | H17: Internship 1,160 (2026); Senior Business Analyst (investment and risk) 3,496 to 5,244 | J17: n/a (position-based disclosure: division heads about 6,536, Q2 2025) | K17: 4 | L17: 7 | M17: 7 | N17: 7 | O17: 7 | P17: =IF(Weights!$B$7=0,0,ROUND((K17*Weights!$B$2+L17*Weights!$B$3+M17*Weights!$B$4+N17*Weights!$B$5+O17*Weights!$B$6)/Weights!$B$7,2)) -> 6.25 | Q17: =IF(P17>=Weights!$B$11,"A",IF(P17>=Weights!$B$12,"B","C")) -> B | R17: karjera.lb.lt or karjera@lb.lt; paid 2 to 3 month internships open to master's students; summer internships advertised in spring | S17: High-signal, accessible public employer; specialist pay bands low (lowest grade reportedly about 1,627, to be checked). | T17: High | U17: https://karjera.lb.lt/pages/praktika-ir-stazuotes
A18: =RANK(P18,$P$2:$P$85,0) -> 16 | B18: Swedbank (Group Treasury, risk quant, trainee programme) | C18: Bank treasury and risk | D18: Vilnius (pan-Baltic roles) | E18: Swedbank, AB (code not verified) | F18: Not found | G18: Analyst Development Trainee, Financial Risk Quant Analyst, junior Private Financial Advice specialist | H18: Not found (Glassdoor Vilnius Analyst about 25,000 to 40,000 per year) | I18: 3708 | J18: 2026 bank-wide (pinokis) | K18: 5 | L18: 6 | M18: 7 | N18: 7 | O18: 7 | P18: =IF(Weights!$B$7=0,0,ROUND((K18*Weights!$B$2+L18*Weights!$B$3+M18*Weights!$B$4+N18*Weights!$B$5+O18*Weights!$B$6)/Weights!$B$7,2)) -> 6.25 | Q18: =IF(P18>=Weights!$B$11,"A",IF(P18>=Weights!$B$12,"B","C")) -> B | R18: Swedbank Analyst Development Trainee Programme (about 10 months of rotations; about 200 trainees per year group-wide) | S18: Programme is group and Stockholm oriented; one alumnus moved into Group Treasury. Risk quant roles ask for VaR/ES experience. | T18: Medium | U18: https://www.swedbank.com/work-with-us/students-and-graduates/swedbank-analyst-development-trainee-program.html
A19: =RANK(P19,$P$2:$P$85,0) -> 18 | B19: Oaklins Baltics (Alpha Advisors UAB) | C19: M&A advisory boutique | D19: Vilnius | E19: Alpha Advisors UAB (inferred; code not confirmed) | F19: Small Vilnius team; 20+ M&A professionals across the Baltics | G19: Analyst | H19: Not found | J19: n/a | K19: 4 | L19: 7 | M19: 9 | N19: 3 | O19: 8 | P19: =IF(Weights!$B$7=0,0,ROUND((K19*Weights!$B$2+L19*Weights!$B$3+M19*Weights!$B$4+N19*Weights!$B$5+O19*Weights!$B$6)/Weights!$B$7,2)) -> 6.2 | Q19: =IF(P19>=Weights!$B$11,"A",IF(P19>=Weights!$B$12,"B","C")) -> B | R19: Networking with partners (Mindaugas Matulaitis, Marius Binkevičius); internships; hired an analyst in 2025 | S19: Most consistent Baltic league-table leader: Mergermarket Baltic adviser of the year 2020 and 2022; 2025 sale of WhiteBit. Analyst intake about 0 to 2 per year. | T19: High | U19: https://www.oaklins.com/baltics/en/team/
A20: =RANK(P20,$P$2:$P$85,0) -> 18 | B20: Lords LB Asset Management | C20: Real estate, PE and VC fund manager | D20: Vilnius | E20: Lords LB Asset Management, UAB, 301849625 | F20: 36 | G20: Fund or investment analyst, asset management analyst | H20: Not found | I20: 6240 | J20: Aug 2026 (info.lt); 6,068 (okredo, to 2025); 7,229 for 2024 (Scoris) | K20: 7 | L20: 6 | M20: 8 | N20: 3 | O20: 6 | P20: =IF(Weights!$B$7=0,0,ROUND((K20*Weights!$B$2+L20*Weights!$B$3+M20*Weights!$B$4+N20*Weights!$B$5+O20*Weights!$B$6)/Weights!$B$7,2)) -> 6.2 | Q20: =IF(P20>=Weights!$B$11,"A",IF(P20>=Weights!$B$12,"B","C")) -> B | R20: Direct application and LinkedIn (hiring channel not documented) | S20: Largest Lithuanian real estate fund manager (about EUR 1.42bn to 1.48bn); first retail fund opened Sep 2026. Hidden high payer, but averages include partners. PE Fund I is opportunistic Belarus commercial real estate (reputational flag). | T20: High | U20: https://lordslb.lt/en/funds/
A21: =RANK(P21,$P$2:$P$85,0) -> 20 | B21: Swedbank (Corporate Finance, DCM and corporate banking) | C21: Bank CIB | D21: Vilnius | E21: Swedbank, AB (code not verified) | F21: Not found | G21: Corporate finance or corporate banking analyst | H21: Not found | I21: 3708 | J21: 2026 bank-wide (pinokis) | K21: 5 | L21: 6 | M21: 8 | N21: 5 | O21: 7 | P21: =IF(Weights!$B$7=0,0,ROUND((K21*Weights!$B$2+L21*Weights!$B$3+M21*Weights!$B$4+N21*Weights!$B$5+O21*Weights!$B$6)/Weights!$B$7,2)) -> 6.15 | Q21: =IF(P21>=Weights!$B$11,"A",IF(P21>=Weights!$B$12,"B","C")) -> B | R21: jobs.swedbank.com; Analyst Development Trainee Programme | S21: #1 Lithuanian bank by loans; Swedbank Corporate Finance lists Vilnius among its offices. No current team list or pay found. | T21: Medium | U21: https://privateequityinfo.com/directory/investment-bank/swedbank-corporate-finance
A22: =RANK(P22,$P$2:$P$85,0) -> 21 | B22: EIB Group (Baltic regional office) | C22: International financial institution | D22: Vilnius | E22: EIB Group office, Liejyklos g. 8 | F22: Small liaison office | G22: Rare local roles; investment officers mainly in Luxembourg | H22: Not found | J22: n/a | K22: 5 | L22: 8 | M22: 8 | N22: 1 | O22: 7 | P22: =IF(Weights!$B$7=0,0,ROUND((K22*Weights!$B$2+L22*Weights!$B$3+M22*Weights!$B$4+N22*Weights!$B$5+O22*Weights!$B$6)/Weights!$B$7,2)) -> 6.05 | Q22: =IF(P22>=Weights!$B$11,"A",IF(P22>=Weights!$B$12,"B","C")) -> B | R22: EIB careers (Luxembourg); use the Vilnius office for networking | S22: Opened 2020; mainly a liaison and regional office. Pay score not evidenced in the notes. | T22: Low | U22: https://www.eib.org/en/contacts/office/lithuania
A23: =RANK(P23,$P$2:$P$85,0) -> 21 | B23: Invalda INVL (listed holding) | C23: Investment holding | D23: Vilnius | E23: AB Invalda INVL, 121304349 | F23: 6 | G23: Investment analyst (rare) | H23: Not advertised | I23: 5245 | J23: okredo (period not stated); 6 staff incl. executives | K23: 6 | L23: 7 | M23: 8 | N23: 1 | O23: 7 | P23: =IF(Weights!$B$7=0,0,ROUND((K23*Weights!$B$2+L23*Weights!$B$3+M23*Weights!$B$4+N23*Weights!$B$5+O23*Weights!$B$6)/Weights!$B$7,2)) -> 6.05 | Q23: =IF(P23>=Weights!$B$11,"A",IF(P23>=Weights!$B$12,"B","C")) -> B | R23: Networking via INVL group | S23: Holds about 19.9% of Artea and over 14% of maib with an INVL fund. Tiny team; average is executive-heavy. | T23: High | U23: https://okredo.com/lt-lt/imone/akcine-bendrove-invalda-invl-121304349
A24: =RANK(P24,$P$2:$P$85,0) -> 21 | B24: Nter Asset Management (Nter Private Debt Fund) | C24: Private credit | D24: Vilnius | E24: Nter Asset Management, UAB, 111707985 (probably formerly Orion Asset Management) | F24: 23 to 25 | G24: Investment Associate, analyst | H24: Not found | I24: 4781 | J24: okredo (2025 to Jan 2026); 4,553 Sep 2025 (tax.lt); 3,079 in 2023 annual report | K24: 6 | L24: 5 | M24: 9 | N24: 4 | O24: 6 | P24: =IF(Weights!$B$7=0,0,ROUND((K24*Weights!$B$2+L24*Weights!$B$3+M24*Weights!$B$4+N24*Weights!$B$5+O24*Weights!$B$6)/Weights!$B$7,2)) -> 6.05 | Q24: =IF(P24>=Weights!$B$11,"A",IF(P24>=Weights!$B$12,"B","C")) -> B | R24: Direct application, LinkedIn | S24: Self-described largest private debt fund in Lithuania (about EUR 100m invested since 2017); also Nter PE Fund I. Named Investment Associate confirms junior seats. | T24: High | U24: https://www.nteram.lt/en/leading-baltic-private-debt-fund
A25: =RANK(P25,$P$2:$P$85,0) -> 24 | B25: Contrarian Ventures | C25: Venture capital (climate tech) | D25: Vilnius | E25: UAB Contrarian Ventures, 304584559 | F25: About 10 | G25: Analyst, Associate | H25: Not found | I25: 4950 | J25: okredo (period not stated); 5,380 for 2024 (Scoris) | K25: 6 | L25: 7 | M25: 7 | N25: 2 | O25: 7 | P25: =IF(Weights!$B$7=0,0,ROUND((K25*Weights!$B$2+L25*Weights!$B$3+M25*Weights!$B$4+N25*Weights!$B$5+O25*Weights!$B$6)/Weights!$B$7,2)) -> 6 | Q25: =IF(P25>=Weights!$B$11,"A",IF(P25>=Weights!$B$12,"B","C")) -> B | R25: LinkedIn, firm site; networking | S25: Pan-European climate-tech seed and Series A investor; Fund II about EUR 100m with EIF anchoring EUR 25m; also manages the Ignitis Smart Energy Fund. | T25: High | U25: https://okredo.com/lt-lt/imone/uab-contrarian-ventures-304584559
A26: =RANK(P26,$P$2:$P$85,0) -> 24 | B26: Nasdaq Vilnius Services | C26: Market infrastructure (exchange, clearing) | D26: Vilnius | E26: Nasdaq Vilnius Services, UAB, 303332886 | F26: 551 to 598 | G26: Issuer Surveillance Analyst, Quantitative Risk Analyst (Nasdaq Clearing), Financial Risk Management Analyst | H26: Not retrievable | I26: 4020 | J26: Sep 2025 (tax.lt); 4,119 Jan to Oct 2025; 4,454 undated | K26: 6 | L26: 6 | M26: 6 | N26: 6 | O26: 6 | P26: =IF(Weights!$B$7=0,0,ROUND((K26*Weights!$B$2+L26*Weights!$B$3+M26*Weights!$B$4+N26*Weights!$B$5+O26*Weights!$B$6)/Weights!$B$7,2)) -> 6 | Q26: =IF(P26>=Weights!$B$11,"A",IF(P26>=Weights!$B$12,"B","C")) -> B | R26: Nasdaq careers, jobsinforex, Work in Lithuania | S26: Clearing risk quant and Stockholm issuer surveillance are front-office adjacent; many tech and cyber roles too. Glassdoor 4.5/5. | T26: High | U26: https://tax.lt/imones/97526-nasdaq-vilnius-services-uab
A27: =RANK(P27,$P$2:$P$85,0) -> 26 | B27: Deloitte Lietuva (Financial Advisory) | C27: Big 4 transaction services | D27: Vilnius | E27: Deloitte Lietuva UAB (code not confirmed) | F27: Not found | G27: Senior Associate Financial Advisory; Audit Analyst as feeder | H27: Senior Associate FA 2,000 to 2,900 (2022); Audit Analyst 1,750 | J27: n/a | K27: 3 | L27: 6 | M27: 8 | N27: 7 | O27: 7 | P27: =IF(Weights!$B$7=0,0,ROUND((K27*Weights!$B$2+L27*Weights!$B$3+M27*Weights!$B$4+N27*Weights!$B$5+O27*Weights!$B$6)/Weights!$B$7,2)) -> 5.95 | Q27: =IF(P27>=Weights!$B$11,"A",IF(P27>=Weights!$B$12,"B","C")) -> B | R27: Deloitte careers, cvonline | S27: Current FA ad shows no salary. | T27: Medium | U27: https://cvonline.lt/en/vacancy/911350/deloitte-lietuva-uab/senior-associate-at-financial-advisory
A28: =RANK(P28,$P$2:$P$85,0) -> 26 | B28: EY Baltic (Strategy and Transactions) | C28: Big 4 transaction services | D28: Vilnius | E28: Ernst & Young Baltic UAB (code not confirmed) | F28: Not found | G28: Junior Strategy and Transactions Consultant | H28: Junior S&T Consultant from 1,400 (undated, likely older) | J28: n/a | K28: 3 | L28: 6 | M28: 8 | N28: 7 | O28: 7 | P28: =IF(Weights!$B$7=0,0,ROUND((K28*Weights!$B$2+L28*Weights!$B$3+M28*Weights!$B$4+N28*Weights!$B$5+O28*Weights!$B$6)/Weights!$B$7,2)) -> 5.95 | Q28: =IF(P28>=Weights!$B$11,"A",IF(P28>=Weights!$B$12,"B","C")) -> B | R28: EY careers, cvonline | S28: Also advertises S&T Manager roles in Vilnius. | T28: Medium | U28: https://www.cvonline.lt/lt/vacancy/888481/ey-ernst-and-young-baltic-uab/junior-strategy-and-transactions-consultant
A29: =RANK(P29,$P$2:$P$85,0) -> 28 | B29: Practica Capital | C29: Venture capital (seed) | D29: Vilnius | E29: Practica Capital Management, UAB, 304875397 (older Practica Capital UAB, 302816037) | F29: Under 10 | G29: VC Analyst | H29: Not stated (VC Analyst ad about 2 years ago) | I29: 4840 | J29: Aug 2026 (1551.lt), volatile: about 4,277 to 7,955; 11,968 in Dec 2023 | K29: 5 | L29: 7 | M29: 7 | N29: 2 | O29: 7 | P29: =IF(Weights!$B$7=0,0,ROUND((K29*Weights!$B$2+L29*Weights!$B$3+M29*Weights!$B$4+N29*Weights!$B$5+O29*Weights!$B$6)/Weights!$B$7,2)) -> 5.75 | Q29: =IF(P29>=Weights!$B$11,"A",IF(P29>=Weights!$B$12,"B","C")) -> B | R29: Applications to info@practica.vc; LinkedIn | S29: Largest Baltic seed fund (Fund III EUR 80m hard cap, EIF-backed; over EUR 130m AUM). Spiky averages reflect partner or carry payouts. Analyst role may relocate to Tallinn. | T29: Medium | U29: https://practica.vc/en/news/practica-capital-closes-eur80-million-fund-committed-to-early-stage-investments-in-the-baltics
A30: =RANK(P30,$P$2:$P$85,0) -> 28 | B30: Danske Bank Lithuania (model validation, risk; FuturePros) | C30: Global bank hub | D30: Vilnius | E30: Danske Bank A/S Lietuvos filialas, 301694694 | F30: 4,387 insured (Aug 2026) | G30: FuturePros trainee, Model Validation Quant, risk analyst | H30: Not retrievable | I30: 4037 | J30: Aug 2026 (4w.lt); 4,248 Jun 2026 (info.lt) | K30: 5 | L30: 5 | M30: 5 | N30: 9 | O30: 6 | P30: =IF(Weights!$B$7=0,0,ROUND((K30*Weights!$B$2+L30*Weights!$B$3+M30*Weights!$B$4+N30*Weights!$B$5+O30*Weights!$B$6)/Weights!$B$7,2)) -> 5.75 | Q30: =IF(P30>=Weights!$B$11,"A",IF(P30>=Weights!$B$12,"B","C")) -> B | R30: FuturePros (paid one-year programme; autumn round 1 to 13 Sep; must study or reside in Lithuania; 80% stay) | S30: Danske's second-biggest site, mostly operations, IT and risk. High-value work is credit risk model validation shared with Copenhagen. Criminal record certificate required for some roles from Jun 2026. | T30: High | U30: https://danskebank.lt/en/career/future-pros
A31: =RANK(P31,$P$2:$P$85,0) -> 30 | B31: Swedbank investicijų valdymas | C31: Asset and pension fund manager | D31: Vilnius | E31: Swedbank investicijų valdymas, UAB, 124815377 | F31: 14 | G31: Junior analyst, risk or compliance | H31: Not found | I31: 3811 | J31: Jan 2026 (info.lt); 3,964 (okredo) | K31: 5 | L31: 6 | M31: 8 | N31: 3 | O31: 6 | P31: =IF(Weights!$B$7=0,0,ROUND((K31*Weights!$B$2+L31*Weights!$B$3+M31*Weights!$B$4+N31*Weights!$B$5+O31*Weights!$B$6)/Weights!$B$7,2)) -> 5.7 | Q31: =IF(P31>=Weights!$B$11,"A",IF(P31>=Weights!$B$12,"B","C")) -> B | R31: jobs.swedbank.com | S31: Largest second-pillar manager by members. Much investing may be done at group level (unverified). Second-pillar opt-out window 2026 to 2027 may slow hiring. | T31: Medium | U31: https://www.info.lt/imones/Swedbank-investicij%C5%B3-valdymas-UAB/2106256
A32: =RANK(P32,$P$2:$P$85,0) -> 30 | B32: Capitalica Asset Management | C32: Real estate fund manager | D32: Vilnius | E32: Capitalica Asset Management, UAB, 304234719 | F32: 9 to 14 | G32: Investment or asset management analyst | H32: Not found | I32: 5027 | J32: cvmarket (period not stated); 6,625 in 2023 annual report; 4,257 Jan 2025 | K32: 6 | L32: 5 | M32: 8 | N32: 3 | O32: 6 | P32: =IF(Weights!$B$7=0,0,ROUND((K32*Weights!$B$2+L32*Weights!$B$3+M32*Weights!$B$4+N32*Weights!$B$5+O32*Weights!$B$6)/Weights!$B$7,2)) -> 5.7 | Q32: =IF(P32>=Weights!$B$11,"A",IF(P32>=Weights!$B$12,"B","C")) -> B | R32: Direct application | S32: AUM EUR 260m (Apr 2026) with a EUR 1bn ambition; Z114 Class A office club deal; Nasdaq-listed bonds. Averages include partners. | T32: High | U32: https://capitalica.lt/funds/
A33: =RANK(P33,$P$2:$P$85,0) -> 32 | B33: INVL Family Office (INVL Financial Advisors) | C33: Wealth management / multi-family office | D33: Vilnius | E33: INVL Family Office (code not found); Category B brokerage licence | F33: Small (not found) | G33: Wealth or investment analyst, adviser | H33: Not found | J33: n/a | K33: 5 | L33: 6 | M33: 7 | N33: 4 | O33: 6 | P33: =IF(Weights!$B$7=0,0,ROUND((K33*Weights!$B$2+L33*Weights!$B$3+M33*Weights!$B$4+N33*Weights!$B$5+O33*Weights!$B$6)/Weights!$B$7,2)) -> 5.65 | Q33: =IF(P33>=Weights!$B$11,"A",IF(P33>=Weights!$B$12,"B","C")) -> B | R33: INVL careers, networking | S33: Leading Baltic multi-family office with over EUR 900m client assets; co-organised the Invalda INVL notes offering (2024). | T33: Medium | U33: https://www.invlfamilyoffice.com/
A34: =RANK(P34,$P$2:$P$85,0) -> 33 | B34: ILTE (national development bank) | C34: Development finance / fund-of-funds | D34: Vilnius | E34: ILTE (formerly UAB Investicijų ir verslo garantijos; code not found) | F34: Not found | G34: Fund-of-funds, structured finance or securitisation analyst | H34: Not found | J34: n/a | K34: 4 | L34: 6 | M34: 8 | N34: 4 | O34: 6 | P34: =IF(Weights!$B$7=0,0,ROUND((K34*Weights!$B$2+L34*Weights!$B$3+M34*Weights!$B$4+N34*Weights!$B$5+O34*Weights!$B$6)/Weights!$B$7,2)) -> 5.6 | Q34: =IF(P34>=Weights!$B$11,"A",IF(P34>=Weights!$B$12,"B","C")) -> B | R34: ILTE news and careers pages | S34: Grew to a EUR 1.5bn portfolio after the Aug 2025 consolidation; Lithuania's first green securitisation; runs VC programmes (MILInvest 2, Akceleratorius 3). | T34: Medium | U34: https://governance.lt/en/vvi/ilte/
A35: =RANK(P35,$P$2:$P$85,0) -> 34 | B35: Superia (Superia LT) | C35: M&A advisory boutique | D35: Vilnius | E35: Superia LT, UAB, 135215985 | F35: About 5 | G35: Analyst | H35: Not found | I35: 2262 | J35: Scoris (period not stated) | K35: 3 | L35: 6 | M35: 9 | N35: 2 | O35: 8 | P35: =IF(Weights!$B$7=0,0,ROUND((K35*Weights!$B$2+L35*Weights!$B$3+M35*Weights!$B$4+N35*Weights!$B$5+O35*Weights!$B$6)/Weights!$B$7,2)) -> 5.55 | Q35: =IF(P35>=Weights!$B$11,"A",IF(P35>=Weights!$B$12,"B","C")) -> B | R35: Networking, direct approach | S35: Claims #1 Baltic M&A adviser by 2025 deal count (self-reported). Low average suggests a junior-heavy local office. | T35: Medium | U35: https://www.superia.lt/news/superia-ranked-1-ma-adviser-baltics-number-transactions
A36: =RANK(P36,$P$2:$P$85,0) -> 34 | B36: Artea bankas (treasury, model risk, financial analysis) | C36: Bank | D36: Vilnius | E36: AB Artea bankas (code not verified) | F36: Not found | G36: Financial Analyst, Model Risk Analyst | H36: Financial Analyst 2,080 to 3,120; Model Risk Analyst 2,600 to 3,890 NET (date unconfirmed) | J36: n/a | K36: 5 | L36: 5 | M36: 7 | N36: 5 | O36: 6 | P36: =IF(Weights!$B$7=0,0,ROUND((K36*Weights!$B$2+L36*Weights!$B$3+M36*Weights!$B$4+N36*Weights!$B$5+O36*Weights!$B$6)/Weights!$B$7,2)) -> 5.55 | Q36: =IF(P36>=Weights!$B$11,"A",IF(P36>=Weights!$B$12,"B","C")) -> B | R36: cvbankas | S36: Formerly Šiaulių bankas (renamed May 2025); total assets about EUR 5.84bn; Invalda INVL is the largest shareholder. | T36: Medium | U36: https://en.cvbankas.lt/finansu-analitikas-e-vilniuje/1-13633361
A37: =RANK(P37,$P$2:$P$85,0) -> 34 | B37: Eika Asset Management | C37: Real estate fund manager | D37: Vilnius | E37: Eika Asset Management, UAB, 304094078 | F37: 19 to 20 | G37: Fund analyst | H37: Not found | I37: 4972 | J37: okredo (Sodra, Oct 2026); 5,132 Aug 2026; 6,853 Jan 2025 | K37: 6 | L37: 5 | M37: 8 | N37: 3 | O37: 5 | P37: =IF(Weights!$B$7=0,0,ROUND((K37*Weights!$B$2+L37*Weights!$B$3+M37*Weights!$B$4+N37*Weights!$B$5+O37*Weights!$B$6)/Weights!$B$7,2)) -> 5.55 | Q37: =IF(P37>=Weights!$B$11,"A",IF(P37>=Weights!$B$12,"B","C")) -> B | R37: Direct application; EIKA group | S37: Arm of a residential developer; Vilnius residential partnership funds. Hidden high payer relative to profile. | T37: High | U37: https://okredo.com/lt-lt/imone/uab-eika-asset-management-304094078
A38: =RANK(P38,$P$2:$P$85,0) -> 34 | B38: Luminor Bank (DCM, markets, risk) | C38: Bank CIB | D38: Vilnius (HQ Tallinn) | E38: Luminor Bank AS Lithuanian branch (code not verified) | F38: Not found | G38: DCM or markets analyst, finance, risk | H38: Not found | J38: n/a | K38: 5 | L38: 5 | M38: 7 | N38: 5 | O38: 6 | P38: =IF(Weights!$B$7=0,0,ROUND((K38*Weights!$B$2+L38*Weights!$B$3+M38*Weights!$B$4+N38*Weights!$B$5+O38*Weights!$B$6)/Weights!$B$7,2)) -> 5.55 | Q38: =IF(P38>=Weights!$B$11,"A",IF(P38>=Weights!$B$12,"B","C")) -> B | R38: Luminor careers, MeetFrank | S38: Sale to OTP Bank signed 20 Jul 2026 (pending ECB approval): organisational uncertainty and possible opportunity. Runs a Baltic DCM desk. | T38: Medium | U38: https://www.luminor.lt/en/news/luminor-plans-provide-debt-capital-markets-services
A39: =RANK(P39,$P$2:$P$85,0) -> 34 | B39: Luminor investicijų valdymas | C39: Asset and pension fund manager | D39: Vilnius | E39: Luminor investicijų valdymas, UAB, 226299280 | F39: 11 (2024) | G39: Junior analyst | H39: Not found | I39: 5138 | J39: 2024 (Scoris) | K39: 6 | L39: 5 | M39: 8 | N39: 2 | O39: 6 | P39: =IF(Weights!$B$7=0,0,ROUND((K39*Weights!$B$2+L39*Weights!$B$3+M39*Weights!$B$4+N39*Weights!$B$5+O39*Weights!$B$6)/Weights!$B$7,2)) -> 5.55 | Q39: =IF(P39>=Weights!$B$11,"A",IF(P39>=Weights!$B$12,"B","C")) -> B | R39: Luminor careers | S39: Highest average among bank-owned managers, but only 11 staff. Parent sale to OTP adds uncertainty. | T39: Medium | U39: https://scoris.lt/imone/226299280
A40: =RANK(P40,$P$2:$P$85,0) -> 34 | B40: SEB (Credit Risk Model Validation, quant) | C40: Bank risk quant | D40: Vilnius | E40: SEB bankas AB / SEB Global Services | F40: Not found | G40: Junior Quantitative Data Analyst, Quantitative Analyst in Credit Risk Model Validation | H40: Junior 2,700 to 3,900 (up to 3 years); Quant Analyst 3,750 to 5,650 | I40: 3830 | J40: 2026 bank-wide (pinokis) | K40: 6 | L40: 5 | M40: 5 | N40: 6 | O40: 6 | P40: =IF(Weights!$B$7=0,0,ROUND((K40*Weights!$B$2+L40*Weights!$B$3+M40*Weights!$B$4+N40*Weights!$B$5+O40*Weights!$B$6)/Weights!$B$7,2)) -> 5.55 | Q40: =IF(P40>=Weights!$B$11,"A",IF(P40>=Weights!$B$12,"B","C")) -> B | R40: SEB careers; stats, maths, econometrics or physics background | S40: Good entry benchmark for quant risk; second-line validation is stats-heavy rather than investing. | T40: High | U40: https://sebgroup.com/career/find-your-new-job/our-vacant-positions/junior-quantitative-data-analyst-in-credit-risk-model-validation--seb-vilnius-7d921d26-4cc0-4d60-9d46-35b508d7920e
A41: =RANK(P41,$P$2:$P$85,0) -> 40 | B41: Tesonet (Investments unit) | C41: Corporate venture / holding investments | D41: Vilnius | E41: Tesonet (entity not specified) | F41: About 10 in investments unit | G41: Investment analyst | H41: Not found | J41: n/a | K41: 5 | L41: 6 | M41: 7 | N41: 2 | O41: 7 | P41: =IF(Weights!$B$7=0,0,ROUND((K41*Weights!$B$2+L41*Weights!$B$3+M41*Weights!$B$4+N41*Weights!$B$5+O41*Weights!$B$6)/Weights!$B$7,2)) -> 5.5 | Q41: =IF(P41>=Weights!$B$11,"A",IF(P41>=Weights!$B$12,"B","C")) -> B | R41: Networking; Head of Investments Eglė Eidimtaitė | S41: Stakes in Nord Security, Oxylabs, Hostinger and Artea; six AI investments (Nov 2025); education platform with INVL PE Fund II. | T41: Medium | U41: https://www.lrt.lt/en/news-in-english/19/2621216/tesonet-s-head-of-investments-sees-the-group-s-future-in-lithuania-this-is-home
A42: =RANK(P42,$P$2:$P$85,0) -> 40 | B42: Coinvest Capital (ILTE) | C42: Venture capital (co-investment fund) | D42: Vilnius | E42: Managed by an ILTE subsidiary (code not found) | F42: Small (not found) | G42: Investment Manager | H42: Investment Manager from 3,300 (posting about 1.5 years old) | J42: n/a | K42: 6 | L42: 5 | M42: 7 | N42: 3 | O42: 6 | P42: =IF(Weights!$B$7=0,0,ROUND((K42*Weights!$B$2+L42*Weights!$B$3+M42*Weights!$B$4+N42*Weights!$B$5+O42*Weights!$B$6)/Weights!$B$7,2)) -> 5.5 | Q42: =IF(P42>=Weights!$B$11,"A",IF(P42>=Weights!$B$12,"B","C")) -> B | R42: ILTE news pages and coinvest.lt; prefers foreign VC/PE experience, a master's degree or CFA progress | S42: Evergreen co-investment fund with EUR 44.3m committed; co-invests with angels and VCs. | T42: Medium | U42: https://www.coinvest.lt/post/join-our-team-as-an-investment-manager
A43: =RANK(P43,$P$2:$P$85,0) -> 42 | B43: SEB investicijų valdymas | C43: Asset and pension fund manager | D43: Vilnius | E43: SEB investicijų valdymas, UAB, 125277981 | F43: 26 | G43: Junior analyst, risk or compliance | H43: Not found | I43: 2549 | J43: Scoris (period not stated); monthly 2,100 to 2,700 in 2024 | K43: 4 | L43: 6 | M43: 8 | N43: 3 | O43: 6 | P43: =IF(Weights!$B$7=0,0,ROUND((K43*Weights!$B$2+L43*Weights!$B$3+M43*Weights!$B$4+N43*Weights!$B$5+O43*Weights!$B$6)/Weights!$B$7,2)) -> 5.45 | Q43: =IF(P43>=Weights!$B$11,"A",IF(P43>=Weights!$B$12,"B","C")) -> B | R43: SEB careers | S43: Passed the EUR 2.5bn second-pillar threshold; local mandate scope unverified. | T43: Medium | U43: https://scoris.lt/en/imone/125277981
A44: =RANK(P44,$P$2:$P$85,0) -> 42 | B44: Artea Asset Management | C44: Asset, pension and alternative funds manager | D44: Vilnius | E44: Artea Asset Management, UAB (code not found) | F44: Not found | G44: Fund or investment analyst | H44: Not found | J44: n/a | K44: 5 | L44: 5 | M44: 8 | N44: 3 | O44: 6 | P44: =IF(Weights!$B$7=0,0,ROUND((K44*Weights!$B$2+L44*Weights!$B$3+M44*Weights!$B$4+N44*Weights!$B$5+O44*Weights!$B$6)/Weights!$B$7,2)) -> 5.45 | Q44: =IF(P44>=Weights!$B$11,"A",IF(P44>=Weights!$B$12,"B","C")) -> B | R44: Artea careers, cvbankas | S44: Largest third-pillar manager (about 40%); absorbed INVL's retail business; alternative funds are mainly fund-of-funds, not direct deals. | T44: Medium | U44: https://www.pensijufondas.lt/uab-artea-asset-management/
A45: =RANK(P45,$P$2:$P$85,0) -> 42 | B45: Green Genius (Modus Group) | C45: Renewables developer (M&A, project finance) | D45: Vilnius | E45: Code not found | F45: Not found | G45: M&A or project finance analyst | H45: Not found | J45: n/a | K45: 5 | L45: 5 | M45: 8 | N45: 3 | O45: 6 | P45: =IF(Weights!$B$7=0,0,ROUND((K45*Weights!$B$2+L45*Weights!$B$3+M45*Weights!$B$4+N45*Weights!$B$5+O45*Weights!$B$6)/Weights!$B$7,2)) -> 5.45 | Q45: =IF(P45>=Weights!$B$11,"A",IF(P45>=Weights!$B$12,"B","C")) -> B | R45: Company careers (no investment postings found) | S45: EBRD took a minority stake of up to EUR 100m, its first outside equity; in-house M&A and project finance. | T45: Medium | U45: https://www.ebrd.com/home/news-and-events/news/2024/ebrd-invests-100-million-in-green-genius.html
A46: =RANK(P46,$P$2:$P$85,0) -> 45 | B46: Civitta | C46: Strategy consulting | D46: Vilnius (HQ Tartu) | E46: UAB Civitta (code not confirmed) | F46: 63 to 69 in Vilnius; group 700 to about 930 | G46: Consultant | H46: Not found | J46: n/a | K46: 4 | L46: 5 | M46: 6 | N46: 6 | O46: 7 | P46: =IF(Weights!$B$7=0,0,ROUND((K46*Weights!$B$2+L46*Weights!$B$3+M46*Weights!$B$4+N46*Weights!$B$5+O46*Weights!$B$6)/Weights!$B$7,2)) -> 5.4 | Q46: =IF(P46>=Weights!$B$11,"A",IF(P46>=Weights!$B$12,"B","C")) -> B | R46: Civitta careers, cvbankas | S46: Largest local strategy consultancy (founder ex-McKinsey); much EU funding work. No MBB office in Vilnius. | T46: Medium | U46: https://www.consultancy.eu/firms/civitta
A47: =RANK(P47,$P$2:$P$85,0) -> 46 | B47: Ministry of Finance (State Treasury Department, debt management) | C47: Public finance | D47: Vilnius | E47: Ministry of Finance | F47: Not found | G47: Specialist in the Borrowing and Investment Division | H47: Not found | J47: n/a | K47: 3 | L47: 6 | M47: 8 | N47: 4 | O47: 6 | P47: =IF(Weights!$B$7=0,0,ROUND((K47*Weights!$B$2+L47*Weights!$B$3+M47*Weights!$B$4+N47*Weights!$B$5+O47*Weights!$B$6)/Weights!$B$7,2)) -> 5.35 | Q47: =IF(P47>=Weights!$B$11,"A",IF(P47>=Weights!$B$12,"B","C")) -> B | R47: Civil service job portal; Kurk Lietuvai for networking | S47: Sovereign debt management; no 2026 job ad or pay data found. | T47: Low | U47: https://finmin.lrv.lt/lt/veiklos-sritys/valstybes-skolos-valdymas/skolinimosi-reglamentavimas/
A48: =RANK(P48,$P$2:$P$85,0) -> 47 | B48: Northern Horizon Capital | C48: Real estate investment manager | D48: Vilnius | E48: Northern Horizon Capital, UAB, 300022971 | F48: 10 (Oct 2026) | G48: Investment or asset management analyst | H48: Not found | J48: n/a (2025 revenue EUR 1.315m) | K48: 5 | L48: 5 | M48: 8 | N48: 2 | O48: 6 | P48: =IF(Weights!$B$7=0,0,ROUND((K48*Weights!$B$2+L48*Weights!$B$3+M48*Weights!$B$4+N48*Weights!$B$5+O48*Weights!$B$6)/Weights!$B$7,2)) -> 5.3 | Q48: =IF(P48>=Weights!$B$11,"A",IF(P48>=Weights!$B$12,"B","C")) -> B | R48: Direct application; group teams in Copenhagen, Helsinki, Stockholm, Tallinn, Berlin | S48: Sold the Baltic Horizon Fund management company in 2025 (AIFM now in Tallinn), so the Vilnius role may shrink. | T48: Medium | U48: https://okredo.com/lt-lt/imone/northern-horizon-capital-uab-300022971
A49: =RANK(P49,$P$2:$P$85,0) -> 48 | B49: LitCapital (Litcapital Fund Management) | C49: Private equity (SMEs) | D49: Vilnius | E49: UAB Litcapital Fund Management (code not found) | F49: Small (not found) | G49: Analyst | H49: Not found | J49: n/a | K49: 4 | L49: 5 | M49: 9 | N49: 2 | O49: 6 | P49: =IF(Weights!$B$7=0,0,ROUND((K49*Weights!$B$2+L49*Weights!$B$3+M49*Weights!$B$4+N49*Weights!$B$5+O49*Weights!$B$6)/Weights!$B$7,2)) -> 5.25 | Q49: =IF(P49>=Weights!$B$11,"A",IF(P49>=Weights!$B$12,"B","C")) -> B | R49: LT VCA network (co-founder of LT VCA) | S49: Management company for informed-investor funds since Nov 2019; thin current data. | T49: Low | U49: https://www.lb.lt/en/sfi-financial-market-participants/uab-litcapital-fund-management
A50: =RANK(P50,$P$2:$P$85,0) -> 48 | B50: TransferGo (FX and Treasury desk) | C50: Fintech (FX trading and treasury) | D50: Vilnius / Kaunas | E50: TransferGo Lithuanian entity not confirmed | F50: Small desk (size unknown) | G50: FX and Treasury Quantitative Analyst/Trader, junior/mid FX trader | H50: 2,200 to 4,000 (older listing tagged Kaunas; asked for 3+ years) | J50: n/a | K50: 5 | L50: 5 | M50: 7 | N50: 3 | O50: 6 | P50: =IF(Weights!$B$7=0,0,ROUND((K50*Weights!$B$2+L50*Weights!$B$3+M50*Weights!$B$4+N50*Weights!$B$5+O50*Weights!$B$6)/Weights!$B$7,2)) -> 5.25 | Q50: =IF(P50>=Weights!$B$11,"A",IF(P50>=Weights!$B$12,"B","C")) -> B | R50: Greenhouse job board; MD Treasury and FX Trading Gediminas Kiveris, CFA posts openings on LinkedIn | S50: Real FX trading seat with automated strategies and AI/ML. Experience usually requested; junior/mid trader opening mentioned by the MD. | T50: Medium | U50: https://job-boards.greenhouse.io/transfergo/jobs/6005765004
A51: =RANK(P51,$P$2:$P$85,0) -> 50 | B51: Grant Thornton Baltic (corporate finance and valuations) | C51: Mid-tier advisory | D51: Vilnius / Kaunas / Klaipėda | E51: Code not confirmed | F51: Not found | G51: Financial consultant (valuations, due diligence, M&A) | H51: Not found | J51: n/a | K51: 3 | L51: 4 | M51: 8 | N51: 6 | O51: 6 | P51: =IF(Weights!$B$7=0,0,ROUND((K51*Weights!$B$2+L51*Weights!$B$3+M51*Weights!$B$4+N51*Weights!$B$5+O51*Weights!$B$6)/Weights!$B$7,2)) -> 5.15 | Q51: =IF(P51>=Weights!$B$11,"A",IF(P51>=Weights!$B$12,"B","C")) -> B | R51: GT job PDFs on its website | S51: Head of financial advisory is reportedly a former Covalis analyst (unverified), a useful networking link. | T51: Medium | U51: https://www.grantthornton.lt/en/locations/vilnius
A52: =RANK(P52,$P$2:$P$85,0) -> 51 | B52: Robinhood Europe | C52: Fintech broker (MiCA CASP and investment firm) | D52: Vilnius | E52: Robinhood Europe, UAB (code not found) | F52: Not disclosed | G52: Risk Officer, compliance, operations | H52: Not found | J52: n/a | K52: 5 | L52: 6 | M52: 5 | N52: 3 | O52: 5 | P52: =IF(Weights!$B$7=0,0,ROUND((K52*Weights!$B$2+L52*Weights!$B$3+M52*Weights!$B$4+N52*Weights!$B$5+O52*Weights!$B$6)/Weights!$B$7,2)) -> 4.95 | Q52: =IF(P52>=Weights!$B$11,"A",IF(P52>=Weights!$B$12,"B","C")) -> C | R52: Robinhood careers, LinkedIn; hires against a roadmap | S52: First MiCA CASP licence issued by the Bank of Lithuania plus Category A brokerage licence; EU hub since Aug 2023. Only old Vilnius postings found, mostly risk and compliance rather than investing. | T52: Medium | U52: https://investlithuania.com/news/us-fintech-giant-robinhood-establishes-first-european-hub-in-lithuania/
A53: =RANK(P53,$P$2:$P$85,0) -> 52 | B53: Allianz Lietuva gyvybės draudimas (pension funds) | C53: Insurance / pension fund manager | D53: Vilnius | E53: Code not found | F53: Not found | G53: Investment or pension fund analyst | H53: Not found | J53: n/a | K53: 4 | L53: 5 | M53: 7 | N53: 3 | O53: 5 | P53: =IF(Weights!$B$7=0,0,ROUND((K53*Weights!$B$2+L53*Weights!$B$3+M53*Weights!$B$4+N53*Weights!$B$5+O53*Weights!$B$6)/Weights!$B$7,2)) -> 4.85 | Q53: =IF(P53>=Weights!$B$11,"A",IF(P53>=Weights!$B$12,"B","C")) -> C | R53: Allianz careers | S53: One of six second-pillar managers (took over Aviva's pension business); the one insurer with local investment management. | T53: Low | U53: https://www.tv3.lt/naujiena/verslas/bankai-ir-ju-pensiju-fondai-slepia-kiek-gyventoju-paprase-grazinti-sukauptus-pinigus-kodel-n1484027
A54: =RANK(P54,$P$2:$P$85,0) -> 52 | B54: FIRSTPICK | C54: Venture capital (pre-seed) | D54: Vilnius | E54: Code not found | F54: Small (2 partners plus team) | G54: Analyst | H54: Not found | J54: n/a | K54: 4 | L54: 5 | M54: 7 | N54: 2 | O54: 6 | P54: =IF(Weights!$B$7=0,0,ROUND((K54*Weights!$B$2+L54*Weights!$B$3+M54*Weights!$B$4+N54*Weights!$B$5+O54*Weights!$B$6)/Weights!$B$7,2)) -> 4.85 | Q54: =IF(P54>=Weights!$B$11,"A",IF(P54>=Weights!$B$12,"B","C")) -> C | R54: LinkedIn, networking with partners | S54: Fund II EUR 25m closed Mar 2026 (about EUR 45m total); ILTE and the Ministry of Economy are LPs. | T54: Medium | U54: https://tech.eu/2026/03/05/firstpick-raises-eur25m-to-find-the-baltics-next-breakout-founders/
A55: =RANK(P55,$P$2:$P$85,0) -> 54 | B55: Evernord Asset Management | C55: Private credit and multi-asset funds | D55: Vilnius | E55: Evernord Asset Management, UAB, 304541337 | F55: About 12 | G55: Fund analyst | H55: Not found | J55: n/a | K55: 4 | L55: 4 | M55: 8 | N55: 3 | O55: 5 | P55: =IF(Weights!$B$7=0,0,ROUND((K55*Weights!$B$2+L55*Weights!$B$3+M55*Weights!$B$4+N55*Weights!$B$5+O55*Weights!$B$6)/Weights!$B$7,2)) -> 4.8 | Q55: =IF(P55>=Weights!$B$11,"A",IF(P55>=Weights!$B$12,"B","C")) -> C | R55: Direct application | S55: Bond, real estate and multi-asset funds; AIFM licence dated 25 Aug 2026 on the Bank of Lithuania list. | T55: Medium | U55: https://scoris.lt/en/imone/304541337
A56: =RANK(P56,$P$2:$P$85,0) -> 54 | B56: Orion Securities | C56: Broker with corporate finance (ECM/DCM) | D56: Vilnius | E56: UAB FMĮ Orion Securities, 122033915 | F56: Not found | G56: Corporate finance or brokerage analyst | H56: Not found | J56: n/a | K56: 4 | L56: 4 | M56: 8 | N56: 3 | O56: 5 | P56: =IF(Weights!$B$7=0,0,ROUND((K56*Weights!$B$2+L56*Weights!$B$3+M56*Weights!$B$4+N56*Weights!$B$5+O56*Weights!$B$6)/Weights!$B$7,2)) -> 4.8 | Q56: =IF(P56>=Weights!$B$11,"A",IF(P56>=Weights!$B$12,"B","C")) -> C | R56: Direct application | S56: Category A brokerage licence; placed Lords LB's first public fund offering. Fined by the Bank of Lithuania in 2015 and 2021; no 2025 or 2026 CF deal found. | T56: Medium | U56: https://www.lb.lt/en/sfi-financial-market-participants/uab-fmi-orion-securities
A57: =RANK(P57,$P$2:$P$85,0) -> 56 | B57: Iron Wolf Capital | C57: Venture capital (deep tech and defence) | D57: Vilnius (London presence) | E57: Iron Wolf Capital Management, UAB, 304711768 | F57: About 4 | G57: Intern, Associate (Warsaw-based) | H57: Not found | I57: 2092 | J57: Scoris (1,761 in 2024) | K57: 3 | L57: 5 | M57: 7 | N57: 3 | O57: 6 | P57: =IF(Weights!$B$7=0,0,ROUND((K57*Weights!$B$2+L57*Weights!$B$3+M57*Weights!$B$4+N57*Weights!$B$5+O57*Weights!$B$6)/Weights!$B$7,2)) -> 4.75 | Q57: =IF(P57>=Weights!$B$11,"A",IF(P57>=Weights!$B$12,"B","C")) -> C | R57: LinkedIn internship posts | S57: Fund II target EUR 100m (about EUR 30m at launch, Jun 2025). Low average suggests junior or part-time staff. | T57: Medium | U57: https://scoris.lt/imone/304711768
A58: =RANK(P58,$P$2:$P$85,0) -> 57 | B58: Accenture Baltics | C58: Consulting | D58: Vilnius | E58: Code not confirmed | F58: Not found | G58: Consultant | H58: Not found | J58: n/a | K58: 4 | L58: 5 | M58: 4 | N58: 6 | O58: 5 | P58: =IF(Weights!$B$7=0,0,ROUND((K58*Weights!$B$2+L58*Weights!$B$3+M58*Weights!$B$4+N58*Weights!$B$5+O58*Weights!$B$6)/Weights!$B$7,2)) -> 4.7 | Q58: =IF(P58>=Weights!$B$11,"A",IF(P58>=Weights!$B$12,"B","C")) -> C | R58: LinkedIn jobs | S58: Posts consulting roles in Vilnius; low finance relevance. | T58: Low | U58: https://lt.linkedin.com/jobs/consultant-jobs?countryRedirected=1
A59: =RANK(P59,$P$2:$P$85,0) -> 58 | B59: Vilniaus prekyba (VP Group) | C59: Investment holding (Maxima owner) | D59: Vilnius | E59: Code not found | F59: Not found | G59: Corporate development or investment analyst (unconfirmed) | H59: Not found | J59: n/a | K59: 4 | L59: 5 | M59: 7 | N59: 1 | O59: 5 | P59: =IF(Weights!$B$7=0,0,ROUND((K59*Weights!$B$2+L59*Weights!$B$3+M59*Weights!$B$4+N59*Weights!$B$5+O59*Weights!$B$6)/Weights!$B$7,2)) -> 4.55 | Q59: =IF(P59>=Weights!$B$11,"A",IF(P59>=Weights!$B$12,"B","C")) -> C | R59: Networking only (no postings found) | S59: Main activity is managing investments in subsidiaries; opaque hiring. | T59: Low | U59: https://en.wikipedia.org/wiki/Vilniaus_prekyba
A60: =RANK(P60,$P$2:$P$85,0) -> 58 | B60: Avia Solutions Group (Vilnius management centre) | C60: Corporate finance | D60: Vilnius (HQ Dublin since 2023) | E60: Code not found | F60: 50+ professionals in the global management centre | G60: Finance or business analyst | H60: Not found | J60: n/a | K60: 4 | L60: 4 | M60: 6 | N60: 4 | O60: 5 | P60: =IF(Weights!$B$7=0,0,ROUND((K60*Weights!$B$2+L60*Weights!$B$3+M60*Weights!$B$4+N60*Weights!$B$5+O60*Weights!$B$6)/Weights!$B$7,2)) -> 4.55 | Q60: =IF(P60>=Weights!$B$11,"A",IF(P60>=Weights!$B$12,"B","C")) -> C | R60: ASG careers | S60: Acquisitive aviation group; postings found are finance and business analyst roles, not M&A. | T60: Low | U60: https://careers.aviasg.com/en/aviation-business-group/avia-solutions-group-career
A61: =RANK(P61,$P$2:$P$85,0) -> 60 | B61: GET Baltic (gas exchange) | C61: Exchange / market infrastructure (energy) | D61: Vilnius | E61: GET Baltic (owned by EEX and Amber Grid; code not confirmed) | F61: Not found | G61: Market operations, trading surveillance (inferred) | H61: Not found | J61: n/a | K61: 4 | L61: 5 | M61: 6 | N61: 2 | O61: 5 | P61: =IF(Weights!$B$7=0,0,ROUND((K61*Weights!$B$2+L61*Weights!$B$3+M61*Weights!$B$4+N61*Weights!$B$5+O61*Weights!$B$6)/Weights!$B$7,2)) -> 4.5 | Q61: =IF(P61>=Weights!$B$11,"A",IF(P61>=Weights!$B$12,"B","C")) -> C | R61: Direct application; EEX group careers | S61: Licensed gas market operator for Lithuania, Latvia/Estonia and Finland; EEX launched Baltic and Finnish gas markets in May 2025. Small team, few seats. | T61: Low | U61: https://www.getbaltic.com/en/trading/exchange-participants/
A62: =RANK(P62,$P$2:$P$85,0) -> 60 | B62: Citadele bankas (Lithuanian branch) | C62: Bank | D62: Vilnius, Kaunas, Klaipėda, Panevėžys, Šiauliai | E62: Citadele Lithuanian branch (code not verified) | F62: Not found | G62: Relationship Manager | H62: Not found | J62: n/a | K62: 4 | L62: 4 | M62: 5 | N62: 5 | O62: 5 | P62: =IF(Weights!$B$7=0,0,ROUND((K62*Weights!$B$2+L62*Weights!$B$3+M62*Weights!$B$4+N62*Weights!$B$5+O62*Weights!$B$6)/Weights!$B$7,2)) -> 4.5 | Q62: =IF(P62>=Weights!$B$11,"A",IF(P62>=Weights!$B$12,"B","C")) -> C | R62: cvonline | S62: Reported 2025 net loss of about EUR 84.7m (unverified, Wikipedia). | T62: Low | U62: https://cvonline.lt/en/vacancy/1350641/citadele-bankas/relationship-manager
A63: =RANK(P63,$P$2:$P$85,0) -> 62 | B63: Open Circle Capital | C63: Venture capital (ICT, robotics) | D63: Vilnius | E63: Code not found | F63: About 5 | G63: Analyst | H63: Not found | J63: n/a | K63: 4 | L63: 4 | M63: 7 | N63: 2 | O63: 5 | P63: =IF(Weights!$B$7=0,0,ROUND((K63*Weights!$B$2+L63*Weights!$B$3+M63*Weights!$B$4+N63*Weights!$B$5+O63*Weights!$B$6)/Weights!$B$7,2)) -> 4.45 | Q63: =IF(P63>=Weights!$B$11,"A",IF(P63>=Weights!$B$12,"B","C")) -> C | R63: Networking | S63: About EUR 20m AUM; tickets EUR 100k to 500k. | T63: Medium | U63: https://www.opencirclecapital.lt/
A64: =RANK(P64,$P$2:$P$85,0) -> 63 | B64: Moody's (Vilnius) | C64: Ratings agency hub | D64: Vilnius | E64: Code not found | F64: Not found | G64: Financial Analyst (advertised), cyber security, back office | H64: Not found (Moody's SOC analyst about 30,000 per year) | J64: n/a | K64: 4 | L64: 5 | M64: 4 | N64: 5 | O64: 4 | P64: =IF(Weights!$B$7=0,0,ROUND((K64*Weights!$B$2+L64*Weights!$B$3+M64*Weights!$B$4+N64*Weights!$B$5+O64*Weights!$B$6)/Weights!$B$7,2)) -> 4.4 | Q64: =IF(P64>=Weights!$B$11,"A",IF(P64>=Weights!$B$12,"B","C")) -> C | R64: Moody's careers, Work in Lithuania | S64: Hub started with back office and HR (2019); no evidence of rating analytics or quant roles. | T64: Low | U64: https://jobs.workinlithuania.com/job-offers/10337-financial-analyst
A65: =RANK(P65,$P$2:$P$85,0) -> 63 | B65: Vastint Lithuania | C65: Real estate developer / investor | D65: Vilnius | E65: Code not found | F65: Not found | G65: Portfolio or development finance analyst | H65: Not found | J65: n/a | K65: 4 | L65: 4 | M65: 6 | N65: 3 | O65: 5 | P65: =IF(Weights!$B$7=0,0,ROUND((K65*Weights!$B$2+L65*Weights!$B$3+M65*Weights!$B$4+N65*Weights!$B$5+O65*Weights!$B$6)/Weights!$B$7,2)) -> 4.4 | Q65: =IF(P65>=Weights!$B$11,"A",IF(P65>=Weights!$B$12,"B","C")) -> C | R65: LinkedIn | S65: In Lithuania since 1998; portfolio management and commercial development (e.g. Business Garden). No analyst hiring data. | T65: Low | U65: https://lt.linkedin.com/company/vastint-lithuania
A66: =RANK(P66,$P$2:$P$85,0) -> 65 | B66: MG Baltic (MG grupė) | C66: Investment holding | D66: Vilnius | E66: Code not found | F66: About 3,920 group | G66: Corporate development or investment analyst (unconfirmed) | H66: Not found | J66: n/a | K66: 4 | L66: 4 | M66: 7 | N66: 1 | O66: 5 | P66: =IF(Weights!$B$7=0,0,ROUND((K66*Weights!$B$2+L66*Weights!$B$3+M66*Weights!$B$4+N66*Weights!$B$5+O66*Weights!$B$6)/Weights!$B$7,2)) -> 4.3 | Q66: =IF(P66>=Weights!$B$11,"A",IF(P66>=Weights!$B$12,"B","C")) -> C | R66: Networking only (no postings found) | S66: About EUR 869m revenue (2024); holds media assets and Apranga. | T66: Low | U66: https://lt.wikipedia.org/wiki/MG_grup%C4%97
A67: =RANK(P67,$P$2:$P$85,0) -> 66 | B67: Akola Group (formerly Linas Agro) | C67: Commodity (grain and agri trading) | D67: Lithuania (location not confirmed in notes) | E67: Akola Group (code not confirmed) | F67: Not found | G67: Commodity trading or finance analyst (unconfirmed) | H67: Not found | J67: n/a | K67: 4 | L67: 4 | M67: 5 | N67: 3 | O67: 5 | P67: =IF(Weights!$B$7=0,0,ROUND((K67*Weights!$B$2+L67*Weights!$B$3+M67*Weights!$B$4+N67*Weights!$B$5+O67*Weights!$B$6)/Weights!$B$7,2)) -> 4.2 | Q67: =IF(P67>=Weights!$B$11,"A",IF(P67>=Weights!$B$12,"B","C")) -> C | R67: Company careers (no ads found) | S67: Named as a plausible agri-trading employer; no current trading or risk ads found. | T67: Low | U67: https://www.getbaltic.com/en/trading/exchange-participants/
A68: =RANK(P68,$P$2:$P$85,0) -> 66 | B68: Orlen Lietuva | C68: Commodity (refining; crude and product procurement) | D68: Mažeikiai | E68: Orlen Lietuva (code not confirmed) | F68: Not found | G68: Procurement, hedging or treasury analyst (unconfirmed) | H68: Not found | J68: n/a | K68: 4 | L68: 4 | M68: 5 | N68: 3 | O68: 5 | P68: =IF(Weights!$B$7=0,0,ROUND((K68*Weights!$B$2+L68*Weights!$B$3+M68*Weights!$B$4+N68*Weights!$B$5+O68*Weights!$B$6)/Weights!$B$7,2)) -> 4.2 | Q68: =IF(P68>=Weights!$B$11,"A",IF(P68>=Weights!$B$12,"B","C")) -> C | R68: Orlen group careers (no ads found) | S68: Plausible commodity-adjacent employer; no trading, risk or quant ads or pay data found. Located outside Vilnius. | T68: Low | U68: https://en.wikipedia.org/wiki/Orlen
A69: =RANK(P69,$P$2:$P$85,0) -> 66 | B69: Elektrum Lietuva (Latvenergo) | C69: Energy supply (B2B, gas exchange participant) | D69: Vilnius | E69: Elektrum Lietuva, UAB (code not confirmed) | F69: 231 (May 2025) | G69: Supply planning, pricing or portfolio analyst (inferred) | H69: Not found | I69: 3317 | J69: May 2025 (tax.lt); monthly 3,120 to 5,271 in Jan to May 2025 | K69: 5 | L69: 3 | M69: 5 | N69: 4 | O69: 4 | P69: =IF(Weights!$B$7=0,0,ROUND((K69*Weights!$B$2+L69*Weights!$B$3+M69*Weights!$B$4+N69*Weights!$B$5+O69*Weights!$B$6)/Weights!$B$7,2)) -> 4.2 | Q69: =IF(P69>=Weights!$B$11,"A",IF(P69>=Weights!$B$12,"B","C")) -> C | R69: Company site, Latvenergo group careers | S69: No Lithuanian trading desk evidenced; group trading appears to sit in Riga. Pays well above national average even without a desk. | T69: Medium | U69: https://tax.lt/imones/935-elektrum-lietuva-uab
A70: =RANK(P70,$P$2:$P$85,0) -> 69 | B70: BRAITIN Investments | C70: Real estate, debt and renewables investor | D70: Vilnius | E70: Code not found | F70: Not found | G70: Investment analyst | H70: Not found | J70: n/a | K70: 4 | L70: 3 | M70: 7 | N70: 2 | O70: 4 | P70: =IF(Weights!$B$7=0,0,ROUND((K70*Weights!$B$2+L70*Weights!$B$3+M70*Weights!$B$4+N70*Weights!$B$5+O70*Weights!$B$6)/Weights!$B$7,2)) -> 4.05 | Q70: =IF(P70>=Weights!$B$11,"A",IF(P70>=Weights!$B$12,"B","C")) -> C | R70: Direct approach | S70: Occupies the former Lewben Investment Management LinkedIn page; relationship to Lewben unclear. | T70: Low | U70: https://lt.linkedin.com/company/lewben-investment-management
A71: =RANK(P71,$P$2:$P$85,0) -> 69 | B71: Investicijų valdymas Prosperus | C71: Alternative fund manager (AIFM) | D71: Vilnius | E71: Investicijų valdymas Prosperus, UAB, 303144788 | F71: Small (not found) | G71: Analyst | H71: Not found | I71: 3198 | J71: 2025 average (Scoris) | K71: 4 | L71: 3 | M71: 7 | N71: 2 | O71: 4 | P71: =IF(Weights!$B$7=0,0,ROUND((K71*Weights!$B$2+L71*Weights!$B$3+M71*Weights!$B$4+N71*Weights!$B$5+O71*Weights!$B$6)/Weights!$B$7,2)) -> 4.05 | Q71: =IF(P71>=Weights!$B$11,"A",IF(P71>=Weights!$B$12,"B","C")) -> C | R71: Direct application | S71: AIFM licence from Feb 2025; scope unclear. | T71: Low | U71: https://scoris.lt/en/imone/303144788
A72: =RANK(P72,$P$2:$P$85,0) -> 71 | B72: Baltic Sandbox Ventures | C72: Venture capital (deep tech, life sciences) | D72: Vilnius | E72: Code not found | F72: Not found | G72: Analyst | H72: Not found | J72: n/a | K72: 3 | L72: 4 | M72: 6 | N72: 2 | O72: 5 | P72: =IF(Weights!$B$7=0,0,ROUND((K72*Weights!$B$2+L72*Weights!$B$3+M72*Weights!$B$4+N72*Weights!$B$5+O72*Weights!$B$6)/Weights!$B$7,2)) -> 4 | Q72: =IF(P72>=Weights!$B$11,"A",IF(P72>=Weights!$B$12,"B","C")) -> C | R72: Networking | S72: Founded 2022; about 20 investments; thin data. | T72: Low | U72: https://www.vestbee.com/insights/articles/lithuanian-startup-and-vc-ecosystem-report
A73: =RANK(P73,$P$2:$P$85,0) -> 72 | B73: Enefit (Eesti Energia) | C73: Energy supply | D73: Vilnius | E73: Enefit, UAB (code not confirmed) | F73: Not found | G73: Supply, pricing or B2B analyst (inferred) | H73: Not found | J73: n/a (tax.lt 2,188 snippet mixed with Elektrum data; unreliable) | K73: 4 | L73: 3 | M73: 5 | N73: 4 | O73: 4 | P73: =IF(Weights!$B$7=0,0,ROUND((K73*Weights!$B$2+L73*Weights!$B$3+M73*Weights!$B$4+N73*Weights!$B$5+O73*Weights!$B$6)/Weights!$B$7,2)) -> 3.95 | Q73: =IF(P73>=Weights!$B$11,"A",IF(P73>=Weights!$B$12,"B","C")) -> C | R73: Company site, Enefit group careers | S73: Retail and B2B supply office; no Lithuanian trading-desk ads found; group trading appears to sit in Tallinn. | T73: Low | U73: https://www.enefit.lt/en/privatiems/apie-mus
A74: =RANK(P74,$P$2:$P$85,0) -> 73 | B74: Citco (Vilnius) | C74: Fund administration | D74: Vilnius | E74: Code not found | F74: 900+ (Invest Lithuania); older profile said about 80 | G74: Trade matching operations, fund accounting | H74: Trade matching operations 2,000 to 2,500 | J74: n/a | K74: 3 | L74: 3 | M74: 3 | N74: 8 | O74: 4 | P74: =IF(Weights!$B$7=0,0,ROUND((K74*Weights!$B$2+L74*Weights!$B$3+M74*Weights!$B$4+N74*Weights!$B$5+O74*Weights!$B$6)/Weights!$B$7,2)) -> 3.9 | Q74: =IF(P74>=Weights!$B$11,"A",IF(P74>=Weights!$B$12,"B","C")) -> C | R74: MeetFrank, Citco careers | S74: Serves hedge funds, but operations rather than investing. | T74: Medium | U74: https://investlithuania.com/success-stories/citco/
A75: =RANK(P75,$P$2:$P$85,0) -> 74 | B75: Alter Domus (Vilnius) | C75: Fund administration | D75: Vilnius | E75: Code not found | F75: About 300 planned | G75: Fund administration, corporate services, payments | H75: Not found | J75: n/a | K75: 3 | L75: 3 | M75: 3 | N75: 7 | O75: 4 | P75: =IF(Weights!$B$7=0,0,ROUND((K75*Weights!$B$2+L75*Weights!$B$3+M75*Weights!$B$4+N75*Weights!$B$5+O75*Weights!$B$6)/Weights!$B$7,2)) -> 3.75 | Q75: =IF(P75>=Weights!$B$11,"A",IF(P75>=Weights!$B$12,"B","C")) -> C | R75: Alter Domus careers | S75: Alternative-assets administrator; back and middle office. | T75: Medium | U75: https://investlithuania.com/news/market-leading-alternative-investment-services-provider-expands-operations-to-vilnius/
A76: =RANK(P76,$P$2:$P$85,0) -> 75 | B76: Mano bankas | C76: Fintech bank | D76: Vilnius | E76: AB Mano bankas (code not found) | F76: 51 to 200 | G76: Finance, risk, credit analyst | H76: Not found | J76: n/a | K76: 3 | L76: 3 | M76: 5 | N76: 4 | O76: 4 | P76: =IF(Weights!$B$7=0,0,ROUND((K76*Weights!$B$2+L76*Weights!$B$3+M76*Weights!$B$4+N76*Weights!$B$5+O76*Weights!$B$6)/Weights!$B$7,2)) -> 3.7 | Q76: =IF(P76>=Weights!$B$11,"A",IF(P76>=Weights!$B$12,"B","C")) -> C | R76: Careers site | S76: CEO ceased to serve from 1 Sep 2026 (leadership change). | T76: Low | U76: https://www.mano.bank/en/news/
A77: =RANK(P77,$P$2:$P$85,0) -> 76 | B77: Paysera LT | C77: Fintech (EMI) | D77: Vilnius | E77: Paysera LT, UAB (code not found) | F77: Not found | G77: Finance control, compliance | H77: Not found | J77: n/a | K77: 3 | L77: 3 | M77: 4 | N77: 5 | O77: 4 | P77: =IF(Weights!$B$7=0,0,ROUND((K77*Weights!$B$2+L77*Weights!$B$3+M77*Weights!$B$4+N77*Weights!$B$5+O77*Weights!$B$6)/Weights!$B$7,2)) -> 3.65 | Q77: =IF(P77>=Weights!$B$11,"A",IF(P77>=Weights!$B$12,"B","C")) -> C | R77: Careers site | S77: Safeguarded funds about EUR 596m, revenue EUR 29m (2025); compliance and operations focus. | T77: Low | U77: https://thebanks.eu/emis/paysera-lt-354718
A78: =RANK(P78,$P$2:$P$85,0) -> 77 | B78: Goindex | C78: Passive pension fund manager | D78: Vilnius | E78: Code not found | F78: Very small | G78: Analyst | H78: Not found | J78: n/a | K78: 3 | L78: 3 | M78: 6 | N78: 2 | O78: 4 | P78: =IF(Weights!$B$7=0,0,ROUND((K78*Weights!$B$2+L78*Weights!$B$3+M78*Weights!$B$4+N78*Weights!$B$5+O78*Weights!$B$6)/Weights!$B$7,2)) -> 3.6 | Q78: =IF(P78>=Weights!$B$11,"A",IF(P78>=Weights!$B$12,"B","C")) -> C | R78: Direct approach | S78: Independent passive second-pillar manager with about EUR 40m. | T78: Low | U78: https://www.lrt.lt/naujienos/verslas/4/2532696/raudonuojanti-birza-veikia-ir-ii-pakopa-kiek-milijonu-isgaravo-nuo-metu-pradzios
A79: =RANK(P79,$P$2:$P$85,0) -> 77 | B79: KN Energies | C79: Commodity infrastructure (Klaipėda LNG and oil terminals) | D79: Klaipėda | E79: KN Energies (code not confirmed) | F79: Not found | G79: Commercial or finance analyst (unconfirmed) | H79: Not found | J79: n/a | K79: 4 | L79: 3 | M79: 4 | N79: 3 | O79: 4 | P79: =IF(Weights!$B$7=0,0,ROUND((K79*Weights!$B$2+L79*Weights!$B$3+M79*Weights!$B$4+N79*Weights!$B$5+O79*Weights!$B$6)/Weights!$B$7,2)) -> 3.6 | Q79: =IF(P79>=Weights!$B$11,"A",IF(P79>=Weights!$B$12,"B","C")) -> C | R79: Company careers (no ads found) | S79: Terminal operator rather than trader; commodity-adjacent only. | T79: Low | U79: https://www.globenewswire.com/news-release/2026/09/10/3359205/0/en/ignitis-to-enter-into-a-long-term-lng-purchase-agreement.html
A80: =RANK(P80,$P$2:$P$85,0) -> 77 | B80: Katalista Ventures | C80: Venture capital / accelerator | D80: Vilnius | E80: Code not found | F80: Not found | G80: Analyst, programme associate | H80: Not found | J80: n/a | K80: 3 | L80: 3 | M80: 6 | N80: 2 | O80: 4 | P80: =IF(Weights!$B$7=0,0,ROUND((K80*Weights!$B$2+L80*Weights!$B$3+M80*Weights!$B$4+N80*Weights!$B$5+O80*Weights!$B$6)/Weights!$B$7,2)) -> 3.6 | Q80: =IF(P80>=Weights!$B$11,"A",IF(P80>=Weights!$B$12,"B","C")) -> C | R80: Networking | S80: Hybrid accelerator and fund; thin data. | T80: Low | U80: https://www.vestbee.com/insights/articles/lithuanian-startup-and-vc-ecosystem-report
A81: =RANK(P81,$P$2:$P$85,0) -> 80 | B81: Galio Group | C81: Real estate developer | D81: Vilnius | E81: Galio Group, UAB (code not confirmed) | F81: Not found | G81: Development finance analyst | H81: Not found | J81: n/a | K81: 3 | L81: 3 | M81: 5 | N81: 3 | O81: 4 | P81: =IF(Weights!$B$7=0,0,ROUND((K81*Weights!$B$2+L81*Weights!$B$3+M81*Weights!$B$4+N81*Weights!$B$5+O81*Weights!$B$6)/Weights!$B$7,2)) -> 3.55 | Q81: =IF(P81>=Weights!$B$11,"A",IF(P81>=Weights!$B$12,"B","C")) -> C | R81: Direct application | S81: Lithuania, Latvia and Poland; 11 projects in pipeline; no hiring data. | T81: Low | U81: https://galio.lt/en/
A82: =RANK(P82,$P$2:$P$85,0) -> 80 | B82: Strategy Labs | C82: Management consulting | D82: Vilnius | E82: Code not confirmed | F82: Not found | G82: Consultant | H82: Not found | J82: n/a | K82: 3 | L82: 3 | M82: 5 | N82: 3 | O82: 4 | P82: =IF(Weights!$B$7=0,0,ROUND((K82*Weights!$B$2+L82*Weights!$B$3+M82*Weights!$B$4+N82*Weights!$B$5+O82*Weights!$B$6)/Weights!$B$7,2)) -> 3.55 | Q82: =IF(P82>=Weights!$B$11,"A",IF(P82>=Weights!$B$12,"B","C")) -> C | R82: Direct application | S82: Vilnius-HQ management consultancy; thin data. | T82: Low | U82: https://craft.co/strategy-labs
A83: =RANK(P83,$P$2:$P$85,0) -> 82 | B83: Achemos grupė (Achema) | C83: Commodity (fertilisers; large gas buyer) | D83: Lithuania (location not confirmed in notes) | E83: Achemos grupė (code not confirmed) | F83: Not found | G83: Gas procurement or hedging analyst (unconfirmed) | H83: Not found | J83: n/a | K83: 4 | L83: 3 | M83: 4 | N83: 2 | O83: 4 | P83: =IF(Weights!$B$7=0,0,ROUND((K83*Weights!$B$2+L83*Weights!$B$3+M83*Weights!$B$4+N83*Weights!$B$5+O83*Weights!$B$6)/Weights!$B$7,2)) -> 3.45 | Q83: =IF(P83>=Weights!$B$11,"A",IF(P83>=Weights!$B$12,"B","C")) -> C | R83: Direct approach (no ads found) | S83: Probably has gas procurement and hedging teams; no group-level investment or trading team information found. | T83: Low | U83: https://en.wikipedia.org/wiki/Achema
A84: =RANK(P84,$P$2:$P$85,0) -> 83 | B84: Western Union Processing Lithuania | C84: Back-office hub (payments operations) | D84: Vilnius | E84: Western Union Processing Lithuania, UAB, 302513944 | F84: 879 to 943 | G84: AML compliance specialist, operations | H84: AML compliance specialist 1,530 to 2,040 | I84: 3545 | J84: Aug 2026 (info.lt); 3,336 Sep 2025 | K84: 3 | L84: 2 | M84: 2 | N84: 8 | O84: 3 | P84: =IF(Weights!$B$7=0,0,ROUND((K84*Weights!$B$2+L84*Weights!$B$3+M84*Weights!$B$4+N84*Weights!$B$5+O84*Weights!$B$6)/Weights!$B$7,2)) -> 3.3 | Q84: =IF(P84>=Weights!$B$11,"A",IF(P84>=Weights!$B$12,"B","C")) -> C | R84: CVMarket, careers site | S84: Operations and compliance; headcount shrinking from an older claim of about 2,000. | T84: High | U84: https://scoris.lt/imone/302513944/darbuotojai_atlyginimai
A85: =RANK(P85,$P$2:$P$85,0) -> 84 | B85: Amicorp (Vilnius) | C85: Fund and corporate administration | D85: Vilnius | E85: Code not found | F85: Not found | G85: Fund administration | H85: Not found | J85: n/a | K85: 3 | L85: 2 | M85: 3 | N85: 4 | O85: 3 | P85: =IF(Weights!$B$7=0,0,ROUND((K85*Weights!$B$2+L85*Weights!$B$3+M85*Weights!$B$4+N85*Weights!$B$5+O85*Weights!$B$6)/Weights!$B$7,2)) -> 2.9 | Q85: =IF(P85>=Weights!$B$11,"A",IF(P85>=Weights!$B$12,"B","C")) -> C | R85: Amicorp site | S85: Offers fund administration, family-office and IB services; small and operations-led. | T85: Low | U85: https://amicorp.com/offices/lithuania/

Sheet Weights
A1: Score | B1: Weight | C1: Notes
A2: Pay score | B2: 0.25 | C2: Default 25%. Column K on Rankings.
A3: Prestige score | B3: 0.25 | C3: Default 25%. Column L on Rankings.
A4: Fit for HEC MIF profile | B4: 0.2 | C4: Default 20%. Column M on Rankings.
A5: Accessibility / hiring likelihood | B5: 0.15 | C5: Default 15%. Column N on Rankings.
A6: Learning and exit opportunities | B6: 0.15 | C6: Default 15%. Column O on Rankings.
A7: Total | B7: =SUM(B2:B6) -> 1 | C7: Weighted totals are divided by this sum, so they stay on a 1 to 10 scale even if it is not 100%.
A8: Check | B8: =IF(ABS(B7-1)<0.00001,"OK","CHECK") -> OK | C8: =IF(ABS(B7-1)<0.00001,"OK: weights sum to 100%","Weights sum to "&TEXT(B7,"0.0%")&"; adjust them to total 100%") -> OK: weights sum to 100%
A10: Tier thresholds
A11: Tier A: minimum weighted total | B11: 6.5 | C11: Default 6.5. Totals at or above this are Tier A.
A12: Tier B: minimum weighted total | B12: 5 | C12: Default 5.0. Totals from this up to the Tier A threshold are Tier B; anything lower is Tier C.
A14: How to use
A15: Edit only the yellow cells with blue text (B2:B6 weights, B11:B12 tier thresholds). Rankings recalculate the weighted total, rank and tier automatically. Row order on Rankings stays as sorted by the default weights; re-sort with the filter on the Weighted total or Rank column after changing weights.
A16: Scores themselves (Rankings K:O, blue text) are also editable inputs, whole numbers 1 to 10.

Sheet Excluded
A1: Company / firm | B1: Category | C1: Exclusion type | D1: Reason | E1: Source URL
A2: Barclays (Vilnius operations centre) | B2: Global bank hub | C2: Exited | D2: Closed in 2019: about 460 jobs moved to HCL Technologies and about 260 redundancies; Swedbank bought the Rise Vilnius fintech centre. | E2: https://www.baltictimes.com/barclays_set_to_close_its_operations_center_in_lithuania__to_lay_off_some_260_people/
A3: Kevin EU, UAB (kevin.) | B3: Fintech (payments) | C3: Insolvent | D3: Insolvency opened by Vilnius Regional Court on 19 Sep 2024; Bank of Lithuania revoked its licence. Its rekvi.lt TOP 100 average (about EUR 13,966) is a tiny-headcount artefact. | E3: https://www.lb.lt/en/news/payment-institution-licence-of-kevin-eu-uab-revoked
A4: Binance / Bifinity UAB | B4: Crypto exchange and payments | C4: Exited | D4: Ceased operations 31 Dec 2025, no MiCA licence, one employee left by Jun 2026. | E4: https://www.lrt.lt/en/news-in-english/19/2957111/binance-withdraws-from-lithuania
A5: Inter RAO Lietuva AB | B5: Energy trading / import | C5: Sanctioned and inactive | D5: Stopped supplying electricity in May 2022; under FNTT sanctions over Putin-linked ties; case referred to the EU Court of Justice; 2026 spin-off plan not confirmed. | E5: https://www.lrt.lt/naujienos/verslas/4/2913025/inter-rao-lietuvos-pertvarka-nesankcionuoti-akcininkai-ketina-kurti-nauja-imone
A6: GPS Capital Markets Europe, UAB | B6: FX payments | C6: Unreliable signal | D6: Average of about EUR 55,828 with only 4 employees (rekvi.lt TOP 100): reflects one or two executives, not junior pay; payments rather than investing. | E6: https://rekvi.lt/en/top100?sort=atlyginimai
A7: AlphaPay, UAB | B7: Payments | C7: Unreliable signal | D7: Average of about EUR 15,693 with 6 employees: tiny-headcount average driven by directors; payments business. | E7: https://rekvi.lt/en/top100?sort=atlyginimai
A8: Onlychain Fintech Limited | B8: Crypto/fintech branch | C8: Unreliable signal | D8: Top Sodra payer in Jan 2026 per TV3 snippet; probably a small branch; crypto/payments; no evidence of investment roles. | E8: https://www.tv3.lt/naujiena/verslas/didziausi-atlyginimai-lietuvoje-sausi-kai-kurios-imones-savo-darbuotojams-mokejo-ir-po-79-tukst-euru-n1498035
A9: Sound asset management, UAB | B9: Fund manager (66.30) | C9: Unreliable signal | D9: Average about EUR 6,800 with 5 employees and a small loss; activity unknown; average likely reflects owners or directors. | E9: https://scoris.lt/en/imone/306274580
A10: Groa Capital | B10: Fund manager (66.30) | C10: Insufficient evidence | D10: Surfaced on Scoris without wage, headcount or activity detail. | E10: https://scoris.lt/imone/304062479
A11: Covalio industry investment, UAB | B11: Unrelated | C11: False match | D11: Kaunas entity with 1 employee; name near-hit for Covalis, unrelated. | E11: https://scoris.eu/company/LT/301870555
A12: Algorithmic Trading Portfolio (Orion AM, Dr Aistis Raudys) | B12: Systematic hedge fund | C12: Exited | D12: Only Lithuanian algorithmic hedge fund; reportedly stopped running in 2021. | E12: https://en.wikipedia.org/wiki/Aistis_Raudys
... A52: Palantir Lithuania, Talech Lithuania, VMware branch, Live Nation Lietuva | B52: Non-finance top Sodra payers | C52: Not finance; unreliable signal | D52: Top national Sodra averages come from tiny non-finance units (e.g. Talech about EUR 117k in one month); shows how volatile small-headcount averages are. | E52: https://rekvi.lt/en/top100?sort=atlyginimai

Sheet Methodology
A1: Topic | B1: Detail
A2: Purpose | B2: Ranks Lithuanian high-finance employers for a Lithuanian MSc International Finance student at HEC Paris (early career, returning to Lithuania) who targets the highest-paying, most prestigious roles. Built only from the research notes in research_notes/Lithuania high finance employers (research date 9 Oct 2026). No new web research was done for this workbook.
A3: Unit of analysis | B3: One row per employer or distinct business unit with a different seat type (e.g. Ignitis trading versus Ignitis corporate finance; SEB CIB versus SEB model validation; INVL PE, INVL renewables and INVL private debt). Excluded firms are on the Excluded sheet.
A4: Weighted total | B4: Weighted total = (Pay x w1 + Prestige x w2 + Fit x w3 + Accessibility x w4 + Opportunities x w5) / sum of weights. Defaults: Pay 25%, Prestige 25%, Fit 20%, Accessibility 15%, Opportunities 15%. Rank = RANK of the total. Tier A at or above 6.5, Tier B at or above 5.0, otherwise C (editable on Weights).
A5: Pay score (1 to 10) | B5: Anchored on realistic early-career pay. 10: advertised base of EUR 5,000+ (VNT 5,000 to 10,000). 9: entity average about EUR 6,000+ across 40+ staff with profit share (Humbility). 8: credible expected pay well above EUR 4,000 for a junior (Covalis, inferred). 7: junior or analyst ads about EUR 3,000 to 5,000 (Ignitis trading, Vinted, Revolut) or a 36-person entity averaging over EUR 6,000 (Lords LB). 6: ads about EUR 2,700 to 4,000 or small-entity averages of EUR 4,500 to 5,700 that include partners. 5: ads about EUR 2,000 to 3,100 or averages about EUR 3,300 to 4,000. 4: entry about EUR 1,150 to 2,500 rising to about EUR 4,000 at senior level, or unknown pay at a mid-sized employer. 3: entry or average below about EUR 2,500. 2: low-paid operations. Entity averages were discounted where partners or executives skew them; firms with no data were scored by peer inference and given lower confidence.
A6: Prestige score (1 to 10) | B6: Global brand, investment-side seniority of the Vilnius work, and selectivity. 9: global hedge fund with investment staff in Vilnius (Covalis). 8: leading Baltic PE and infrastructure houses (INVL PE, BaltCap, Livonia) and the EIB. 7: top M&A boutique (Oaklins), selective quant/prop firms (Humbility, VNT), Ignitis trading, top VC (Contrarian, Practica), Bank of Lithuania, INVL fund teams. 6: Big 4 deals, bank CIB and treasury, Revolut, Nasdaq, Vinted, Ignitis corporate finance, Lords LB. 5: mid-sized managers, bank quant hubs, consulting, smaller VCs. 3 to 4: small or opaque managers, corporates without investment teams. 2: back-office hubs.
A7: Fit for HEC MIF profile (1 to 10) | B7: Relevance of the day-to-day work to a finance master's. 10: buy-side public-equity research. 9: PE, private debt investing, M&A advisory. 8: transaction services, corporate banking and project finance, asset management, treasury, IR, development finance. 7: trading analyst, VC, central bank, FX treasury. 6: quant risk at exchanges, consulting. 5: model validation, energy supply. 4: pure software or signal-processing quant roles (Humbility, VNT), ratings back office. 2 to 3: operations, compliance, fund administration.
A8: Accessibility / hiring likelihood (1 to 10) | B8: Number of seats and whether fresh graduates are hired. 9: structured graduate programme with many seats (Danske FuturePros). 8: Big 4 intakes and large operations hubs. 7: Bank of Lithuania internships, Swedbank trainee programme, other large employers with junior ads. 5 to 6: mid-size employers with occasional junior or analyst ads (INVL, Ignitis, SEB). 3 to 4: small teams that occasionally hire analysts. 1 to 2: a handful of seats, no ads, experience normally required (Covalis, Livonia, VNT, holdings).
A9: Learning and exit opportunities (1 to 10) | B9: Skill build and the doors the role opens. 9: global buy-side (Covalis). 8: PE deal teams, M&A boutiques, Big 4 deals (classic exits to PE and corporate development). 7: trading desks, quant firms, VC, central bank, bank CIB, international bank treasury. 6: asset management subsidiaries, quant risk, corporate finance at large corporates. 4 to 5: niche managers, holdings, supply companies. 2 to 3: back office.
A10: Data confidence | B10: High: Lithuanian presence confirmed plus entity pay data and/or salary-bearing job ads from multiple sources. Medium: presence confirmed but pay, team size or hiring channel partly inferred. Low: presence plausible from the notes, little or no role or pay evidence.
A11: Main data caveat | B11: Direct Lithuanian sources (rekvizitai.vz.lt, atvira.sodra.lt, lb.lt, Registrų centras, cvbankas.lt and others) were blocked by the research environment's proxy. Most figures therefore come from search-engine summaries of Sodra-based aggregators (okredo, tax.lt, scoris.lt, info.lt, 1551.lt, 4w.lt, lovejob.lt, rekvi.lt, fsaskaita.lt) and of job boards, not from full page reads. Aggregators disagree by month and method. Treat all figures as indicative and verify before relying on them.
A12: Entity averages include partners | B12: Sodra-based averages are gross monthly pay across all insured staff of the legal entity, including partners, directors and back office. In small firms (under about 15 staff) they are dominated by senior pay and swing heavily in bonus or carry months (e.g. Practica about EUR 4,300 to 12,000; Humbility spike about EUR 40,300). Junior pay at PE, VC and real estate boutiques is probably EUR 2,000 to 3,500 gross, in line with job ads. Some firms (Covalis, Livonia) have no Lithuanian entity, so no Sodra data exists.
... A21: Style | B21: Pay ranges are written with 'to'. Scores are inputs (blue text) and can be overridden; totals, ranks and tiers are formulas.

Sheet Networking and paths
A1: Channel / programme | B1: Type | C1: What it is and why it matters | D1: Timing, eligibility and pay | E1: How to use it | F1: Source URL
A2: Global Lithuanian Leaders (GLL) | B2: Diaspora professional network | C2: 10,000+ global Lithuanian professionals in 60+ countries and 28 clubs; best broad door into Lithuanian business and finance leaders. | D2: GLL Forum held 30 Jul 2026 in Vilnius; GLL Awards on 21 Dec 2026. | E2: Join a club (Paris), attend the Forum and Awards, ask for introductions to INVL, BaltCap, Oaklins and Ignitis people. | F2: https://lithuanianleaders.org/
A3: LT Big Brother (run with GLL) | B3: Mentoring programme | C3: Pairs established Lithuanian professionals with students and early-career people; started in London in 2009; six regions incl. Lithuania, UK and Benelux (self-reported). | D3: Check ltbigbrother.com for the intake calendar (site not fetched). | E3: Request a mentor in PE, hedge funds or M&A. | F3: https://lt.linkedin.com/in/jonas-kimontas
A4: Kurk Lietuvai (Create Lithuania) | B4: Government programme | C4: One-year public-sector project placements for professionals with foreign experience; builds ties with Ministry of Finance, Invest Lithuania and Bank of Lithuania circles. | D4: 2026 cycle results presented 8 Sep 2026; public-sector pay. | E4: Networking and visibility route rather than a high-pay entry. | F4: https://www.kurklt.lt/en
A5: Bank of Lithuania internships | B5: Internship | C5: Paid 2 to 3 month internships (2 to 6 per another listing) in market operations, financial stability and supervision; open to master's students. | D5: About EUR 1,160 gross per month (2026 example); summer internships advertised in spring (example deadline 28 Apr 2026). | E5: Apply via karjera.lb.lt or send a CV to karjera@lb.lt. | F5: https://karjera.lb.lt/pages/praktika-ir-stazuotes
A6: Danske Bank FuturePros | B6: Graduate programme | C6: Paid one-year career start programme, no prior experience needed; 80% continue at Danske Lithuania. Historic Danske Graduate: 18 months, three 6-month rotations, possibly one in Scandinavia. | D6: Autumn 2026 round ran 1 to 13 Sep (closed); must study or reside in Lithuania. | E6: Target the next round; aim for risk, model validation or treasury rotations. | F6: https://danskebank.lt/en/career/future-pros
A7: Swedbank Analyst Development Trainee Programme | B7: Graduate programme | C7: About 10 months of rotations; about 200 trainees a year group-wide (mostly IT and Data, Finance and Analysis); one alumnus became a Group Treasury analyst. | D7: Group and Stockholm oriented; timing not confirmed in notes. | E7: Apply via swedbank.com students and graduates; also junior Private Financial Advice roles in Vilnius. | F7: https://www.swedbank.com/work-with-us/students-and-graduates/swedbank-analyst-development-trainee-program.html
A8: SEB Tech Trainee Programme and SEB junior quant roles | B8: Graduate programme / junior roles | C8: Tech programme: 6 months from September, up to 20 trainees, graduates within 2 years (tech only). Better finance entry: Junior Quantitative Data Analyst in Credit Risk Model Validation (EUR 2,700 to 3,900). | D8: 2026/27 Vilnius tech intake posted Jun 2026; junior quant ad valid to Dec 2026 per one listing. | E8: Use SEB careers; for CIB, Client Analyst roles in Corporate Banking. | F8: https://sebgroup.com/career/graduates-and-students/tech-trainee-programme
A9: Ignitis Young Talents and internships | B9: Internships / trainee roles | C9: Group Treasury, IR and FP&A teams named on the young talents page; FP&A trainee ads; Ignitis Renewables young talents page. | D9: FP&A trainee EUR 1,240 to 1,860; a 2026 legal internship paid about EUR 650 to 950. | E9: Enter via trainee or analyst roles, then move toward trading, treasury or M&A. | F9: https://ignitisgrupe.lt/en/career/young-talents
A10: Big 4 internships and trainee intakes (PwC, KPMG, EY, Deloitte) | B10: Internships / graduate intakes | C10: Largest structured entry into deals work in Vilnius; classic springboard to PE (BaltCap and Livonia associates often come from Big 4 TS or IB). | D10: KPMG interns from EUR 1,153 to 1,245; EY junior S&T from EUR 1,400; hiring follows the academic calendar (no deals-specific programme confirmed). | E10: Apply directly to Deals / Deal Advisory / S&T teams. | F10: https://www.cvbankas.lt/intern-in-advisory-sales-vilniuje/1-14124490
A11: ECB traineeships | B11: International traineeship | C11: 3 to 6 months (extendable), open to EU nationals; Banking Supervision traineeships. | D11: Grant EUR 1,170 to 2,120 per month; Frankfurt. | E11: High-signal step before Bank of Lithuania or supervision roles. | F11: https://www.ecb.europa.eu/careers/pdf/traineeship_programme.pdf
A12: LT VCA (Lithuanian Private Equity and Venture Capital Association) | B12: Industry association | C12: 64 members, 243 portfolio companies, EUR 3bn AUM; co-founded in 2009 by BaltCap, LitCapital and SEB Venture Capital; runs events and a YouTube channel. | D12: Ongoing events. | E12: Best channel to meet PE and VC partners (INVL, BaltCap, Livonia, Practica, Contrarian). | F12: https://www.vca.lt/
... A20: Abroad-first path | B20: Career strategy | C20: Lithuanian pay and deal flow are regionally capped; MBB has no Vilnius office and global HFT/hedge funds have no Vilnius teams. Common path: start in London, Paris, Warsaw or the Nordics (IB, MBB, energy desks such as Statkraft, Axpo, Danske Commodities) and return at a senior level. Gravity Team in Riga is a nearby crypto market-maker option. | D20: n/a | E20: Keep Lithuanian network warm through GLL and LT VCA while abroad. | F20: https://www.gravityteam.co/careers
